{"resultCode":1,"resultMsg":"操作成功","systemTime":1749983639313,"data":{"interleavePropagandaList":[[{"id":66,"imgSrc":"https://imagecloud.thepaper.cn/recommend/xuanchuanwei/20241025182414078_2_2_d823584f-6d27-4470-905e-fe699b80a73d.png","imgWidth":720,"imgHeight":270,"link":"https://www.pai-tech.net/","type":1}],[{"id":67,"imgSrc":"https://imagecloud.thepaper.cn/recommend/xuanchuanwei/20240904172338577_3_2_bbbfced3-9ab2-45ba-b20f-975333c0f4f8.jpg","imgWidth":720,"imgHeight":270,"link":"https://tousu.thepaper.cn/www/","type":1},{"id":68,"imgSrc":"https://imagecloud.thepaper.cn/recommend/xuanchuanwei/20240511110623297_3_3_1d6a132d-5d23-45b8-b5b7-b637924698d3.jpg","imgWidth":480,"imgHeight":180,"link":"https://www.thepaper.cn/newsDetail_forward_27325323","type":1}],[{"id":73,"imgSrc":"https://imagecloud.thepaper.cn/recommend/xuanchuanwei/20220812145322429_4_7_80d7d312-d32e-4e3b-b6ac-a1d0e917b207.jpg","imgWidth":200,"imgHeight":75,"link":"","type":1},{"id":74,"imgSrc":"https://imagecloud.thepaper.cn/recommend/xuanchuanwei/20220812145322502_4_8_c70c98db-41e9-46da-b700-9db3fc6c50b2.png","imgWidth":600,"imgHeight":225,"link":"","type":1},{"id":75,"imgSrc":"https://imagecloud.thepaper.cn/recommend/xuanchuanwei/20220812145322525_4_9_88c7dd2b-3091-423e-8319-5890aa745e8f.jpg","imgWidth":200,"imgHeight":75,"link":"https://newsxmwb.xinmin.cn/special/mljbzsjs/index.html","type":1},{"id":76,"imgSrc":"https://imagecloud.thepaper.cn/recommend/xuanchuanwei/20230628161703112_4_10_8437f3f3-89ae-4cc6-90fe-a9ab27640140.jpg","imgWidth":400,"imgHeight":180,"link":"https://www.thepaper.cn/newsDetail_forward_128593","type":1},{"id":69,"imgSrc":"https://imagecloud.thepaper.cn/recommend/xuanchuanwei/20220809142338266_4_2_ef4aba58-ed61-4a3d-963d-b572e06202d8.jpg","imgWidth":200,"imgHeight":75,"link":"https://www.12377.cn","type":1},{"id":70,"imgSrc":"https://imagecloud.thepaper.cn/recommend/xuanchuanwei/20220809142338298_4_3_990e577f-c051-4b7a-84fe-6247eb4913a0.jpg","imgWidth":200,"imgHeight":75,"link":"http://www.shjbzx.cn","type":1},{"id":71,"imgSrc":"https://imagecloud.thepaper.cn/recommend/xuanchuanwei/20220809142338440_4_5_deb0b110-a35d-46d5-9065-953ac61d5cdc.jpg","imgWidth":200,"imgHeight":75,"link":"https://www.12377.cn","type":1},{"id":72,"imgSrc":"https://imagecloud.thepaper.cn/recommend/xuanchuanwei/20220809142338492_4_6_6378a6e4-6574-4da7-9d10-803bbdb33e66.jpg","imgWidth":200,"imgHeight":75,"link":"http://www.cyberpolice.cn/wfjb/ ","type":1}]],"morningEveningNews":[{"name":"中东危局48小时","nodeId":155501,"contType":0,"cardMode":"101","praiseStyle":0,"isSustainedFly":0,"softLocType":0,"paywalled":false},{"contId":"30985315","isOutForword":"0","isOutForward":"0","forwardType":"0","mobForwardType":2,"interactionNum":"59","praiseTimes":"135","imgCardMode":0,"smallPic":"https://imgpai.thepaper.cn/newpai/image/1749912648413_tkMfDK_1749912648636.png?x-oss-process=image/resize,w_332","sharePic":"https://imgpai.thepaper.cn/newpai/image/1749912648349_3dsYf2_1749912648638.png","pubTime":"19小时前","pubTimeNew":"19小时前","summary":"王毅说，中方明确谴责以色列侵犯伊朗的主权、安全和领土完整。","name":"王毅分别同伊朗以色列外长通电话","closePraise":"0","nodeInfo":{"nodeId":122905,"name":"大国外交","desc":"构建人类命运共同体","pic":"https://imagecloud.thepaper.cn/thepaper/image/225/728/225.png","nodeType":0,"channelType":0,"forwordType":22,"forwardType":"22","liveType":"2","parentId":25388,"isOrder":"0","dataType":"0","shareName":"大国外交","nickName":"","publishTime":1668726187654,"mobForwardType":"22","summarize":"构建人类命运共同体","color":"","videoLivingRoomDes":"","wwwSpecNodeAlign":0,"govAffairsType":"","showSpecialBanner":false,"showSpecialTopDesc":false,"topBarTypeCustomColor":false,"showVideoBottomRightBtn":false},"nodeId":122905,"contType":1,"pubTimeLong":1749911864955,"specialNodeId":0,"cardMode":"101","dataObjId":52,"closeFrontComment":false,"isSupInteraction":false,"tagList":[{"tagId":6201,"tag":"王毅","isOrder":"0","isUpdateNotify":"0","isWonderfulComments":"0"},{"tagId":4074,"tag":"伊朗","isOrder":"0","isUpdateNotify":"0","isWonderfulComments":"0"},{"tagId":31530,"tag":"中东局势","isOrder":"0","isUpdateNotify":"0","isWonderfulComments":"0"}],"hideVideoFlag":false,"praiseStyle":1,"isSustainedFly":0,"softLocType":1,"closeComment":false,"voiceInfo":{"voiceSrc":"https://audios.thepaper.cn/input/30985315_202506142244a7bfb2da-34c3-4abb-8338-1da21695bd61.mp3","imgSrc":"https://imgpai.thepaper.cn/newpai/image/1749912648349_3dsYf2_1749912648638.png","isHaveVoice":"1"},"softAdTypeStr":"1,1,1","originalContId":30985315,"paywalled":false,"audiovisualBlogSwitch":false,"audiovisualBlogGuests":""},{"contId":"30986551","isOutForword":"0","isOutForward":"0","forwardType":"0","mobForwardType":2,"interactionNum":"","praiseTimes":"4","imgCardMode":0,"smallPic":"https://imgpai.thepaper.cn/newpai/image/1749935838482_tNS8cM_1749935838845.png?x-oss-process=image/resize,w_332","sharePic":"https://imgpai.thepaper.cn/newpai/image/1749935838560_N5PNB2_1749935838847.png","pubTime":"13小时前","pubTimeNew":"13小时前","summary":"为避免影响关键行业运转，特朗普政府已暂停在农田、餐馆和酒店等地抓捕非法移民。","name":"美暂停在“关键行业”场所抓移民","closePraise":"0","nodeInfo":{"nodeId":25429,"name":"全球速报","desc":"最热点的全球资讯","pic":"https://imagecloud.thepaper.cn/thepaper/image/4/158/73.png","nodeType":0,"channelType":0,"forwordType":22,"forwardType":"22","liveType":"2","parentId":25388,"isOrder":"0","dataType":"0","shareName":"全球速报","nickName":"","publishTime":1668726066292,"mobForwardType":"22","summarize":"最热点的全球资讯","color":"","videoLivingRoomDes":"","wwwSpecNodeAlign":0,"govAffairsType":"","showSpecialBanner":false,"showSpecialTopDesc":false,"topBarTypeCustomColor":false,"showVideoBottomRightBtn":false},"nodeId":25429,"contType":1,"pubTimeLong":1749935751441,"specialNodeId":0,"cardMode":"101","dataObjId":52,"closeFrontComment":false,"isSupInteraction":false,"tagList":[{"tagId":33,"tag":"美国","isOrder":"0","isUpdateNotify":"0","isWonderfulComments":"0"}],"hideVideoFlag":false,"praiseStyle":1,"isSustainedFly":0,"softLocType":1,"closeComment":false,"voiceInfo":{"voiceSrc":"https://audios.thepaper.cn/input/30986551_20250615051639c5f04b-fae4-4669-b859-467d253f3e45.mp3","imgSrc":"https://imgpai.thepaper.cn/newpai/image/1749935838560_N5PNB2_1749935838847.png","isHaveVoice":"1"},"softAdTypeStr":"1,1,1","originalContId":30986551,"paywalled":false,"audiovisualBlogSwitch":false,"audiovisualBlogGuests":""}],"financialInformationNews":[{"contId":"30987304","isOutForword":"0","isOutForward":"0","forwardType":"67","mobForwardType":67,"pic":"","imgCardMode":0,"isDefaultPic":true,"smallPic":"","sharePic":"","pubTime":"4小时前","pubTimeNew":"4小时前","name":"报告：合资金融机构在培育中国特色金融文化方面肩负着独特使命","closePraise":"0","nodeInfo":{"name":"澎湃财讯","desc":"","nodeType":0,"channelType":0,"forwardType":"22","liveType":"1","parentId":0,"isOrder":"0","dataType":"0","shareName":"澎湃财讯","nickName":"","publishTime":1618889006598,"mobForwardType":"22","summarize":"","color":"","videoLivingRoomDes":"","wwwSpecNodeAlign":0,"govAffairsType":"","showSpecialBanner":false,"showSpecialTopDesc":false,"topBarTypeCustomColor":false,"showVideoBottomRightBtn":false},"nodeId":105435,"contType":13,"pubTimeLong":1749968799138,"specialNodeId":0,"cardMode":"101","dataObjId":52,"closeFrontComment":false,"isSupInteraction":false,"hideVideoFlag":false,"praiseStyle":1,"isSustainedFly":0,"softLocType":1,"closeComment":false,"voiceInfo":{"imgSrc":"","isHaveVoice":"0"},"softAdTypeStr":"1,1,1","originalContId":30987304,"paywalled":false},{"contId":"30986902","isOutForword":"0","isOutForward":"0","forwardType":"67","mobForwardType":67,"pic":"https://imagecloud.thepaper.cn/thepaper/image/350/397/529.png","imgCardMode":0,"smallPic":"https://imagecloud.thepaper.cn/thepaper/image/350/397/529.png?x-oss-process=image/resize,w_332","sharePic":"https://imagecloud.thepaper.cn/thepaper/image/350/397/526.jpg","pubTime":"6小时前","pubTimeNew":"6小时前","name":"王长田：预计《哪吒2》海外票房将超过1亿美元  ","closePraise":"0","nodeInfo":{"name":"澎湃财讯","desc":"","nodeType":0,"channelType":0,"forwardType":"22","liveType":"1","parentId":0,"isOrder":"0","dataType":"0","shareName":"澎湃财讯","nickName":"","publishTime":1618889006598,"mobForwardType":"22","summarize":"","color":"","videoLivingRoomDes":"","wwwSpecNodeAlign":0,"govAffairsType":"","showSpecialBanner":false,"showSpecialTopDesc":false,"topBarTypeCustomColor":false,"showVideoBottomRightBtn":false},"nodeId":105435,"contType":13,"pubTimeLong":1749959383302,"specialNodeId":0,"cardMode":"101","dataObjId":52,"closeFrontComment":false,"isSupInteraction":false,"hideVideoFlag":false,"praiseStyle":1,"isSustainedFly":0,"softLocType":1,"closeComment":false,"voiceInfo":{"imgSrc":"https://imagecloud.thepaper.cn/thepaper/image/350/397/526.jpg","isHaveVoice":"0"},"softAdTypeStr":"1,1,1","originalContId":30986902,"paywalled":false}],"hotNews":[{"contId":"30984890","isOutForword":"0","isOutForward":"0","forwardType":"0","mobForwardType":2,"interactionNum":"103","praiseTimes":"139","pic":"https://imgpai.thepaper.cn/newpai/image/1749902081372_TkaFYr_1749902081600.png","imgCardMode":0,"smallPic":"https://imgpai.thepaper.cn/newpai/image/1749902081372_TkaFYr_1749902081600.png?x-oss-process=image/resize,w_332","sharePic":"https://imgpai.thepaper.cn/newpai/image/1749902081375_CNp4AQ_1749902081487.png","pubTime":"22小时前","pubTimeNew":"22小时前","name":"央视新闻评LABUBU爆火：中国潮玩，何以潮向世界？","closePraise":"0","nodeInfo":{"nodeId":25489,"name":"舆论场","desc":"倾听复杂世界的弦外之音","pic":"https://imagecloud.thepaper.cn/thepaper/image/4/158/63.png","nodeType":0,"channelType":0,"forwordType":22,"forwardType":"22","liveType":"2","parentId":25388,"isOrder":"0","dataType":"0","shareName":"舆论场","nickName":"","mobForwardType":"22","summarize":"无论是微博、微信，还是报刊阵地，舆论从来不是铁板一块，意见争论绝无对错之分，我们剖析一场舆论风暴如何发酵，力图每个节点都清晰可循。","color":"","videoLivingRoomDes":"","wwwSpecNodeAlign":0,"govAffairsType":"","showSpecialBanner":false,"showSpecialTopDesc":false,"topBarTypeCustomColor":false,"showVideoBottomRightBtn":false},"nodeId":25489,"contType":0,"pubTimeLong":1749902825134,"specialNodeId":0,"cardMode":"101","dataObjId":52,"closeFrontComment":false,"isSupInteraction":false,"tagList":[{"tagId":6196289,"tag":"LABUBU","isOrder":"0","isUpdateNotify":"0","isWonderfulComments":"0"},{"tagId":2063105,"tag":"潮玩","isOrder":"0","isUpdateNotify":"0","isWonderfulComments":"0"},{"tagId":22206,"tag":"IP","isOrder":"0","isUpdateNotify":"0","isWonderfulComments":"0"}],"hideVideoFlag":false,"praiseStyle":1,"isSustainedFly":0,"softLocType":1,"closeComment":false,"voiceInfo":{"voiceSrc":"https://audios.thepaper.cn/input/30984890_202506142233e0706899-011c-4e06-9956-59faeb27ae2b.mp3","imgSrc":"https://imgpai.thepaper.cn/newpai/image/1749902081375_CNp4AQ_1749902081487.png","isHaveVoice":"1"},"softAdTypeStr":"1,1,1","originalContId":30984890,"paywalled":false,"audiovisualBlogSwitch":false,"audiovisualBlogGuests":""},{"contId":"30984380","isOutForword":"0","isOutForward":"0","forwardType":"0","mobForwardType":2,"interactionNum":"62","praiseTimes":"193","pic":"https://imgpai.thepaper.cn/newpai/image/1749884402770_rjAxCx_1749884402983.png","imgCardMode":0,"smallPic":"https://imgpai.thepaper.cn/newpai/image/1749884402770_rjAxCx_1749884402983.png?x-oss-process=image/resize,w_332","sharePic":"https://imgpai.thepaper.cn/newpai/image/1749884402773_xRynrP_1749884403027.png","pubTime":"22小时前","pubTimeNew":"22小时前","name":"会计江湖｜车圈恒大论背后的供应链融资：是核心竞争力还是风险","closePraise":"0","nodeInfo":{"nodeId":25485,"name":"澎湃商学院","desc":"品牌课外书，生活经济学","pic":"https://imagecloud.thepaper.cn/thepaper/image/4/158/91.png","nodeType":0,"channelType":0,"forwordType":22,"forwardType":"22","liveType":"2","parentId":25388,"isOrder":"0","dataType":"0","shareName":"澎湃商学院","nickName":"","mobForwardType":"22","summarize":"品牌课外书，生活经济学。聚焦品牌事件、营销案例，盘算身边经济账。","color":"","videoLivingRoomDes":"","wwwSpecNodeAlign":0,"govAffairsType":"","showSpecialBanner":false,"showSpecialTopDesc":false,"topBarTypeCustomColor":false,"showVideoBottomRightBtn":false},"nodeId":25485,"contType":0,"pubTimeLong":1749902916020,"specialNodeId":0,"cardMode":"101","dataObjId":52,"closeFrontComment":false,"isSupInteraction":false,"tagList":[{"tagId":3556093,"tag":"会计江湖","isOrder":"0","isUpdateNotify":"0","isWonderfulComments":"0"},{"tagId":6852818,"tag":"车圈恒大","isOrder":"0","isUpdateNotify":"0","isWonderfulComments":"0"},{"tagId":6882160,"tag":"供应链融资","isOrder":"0","isUpdateNotify":"0","isWonderfulComments":"0"},{"tagId":3480299,"tag":"袁敏","isOrder":"0","isUpdateNotify":"0","isWonderfulComments":"0"}],"hideVideoFlag":false,"praiseStyle":1,"isSustainedFly":0,"softLocType":1,"closeComment":false,"voiceInfo":{"voiceSrc":"https://audios.thepaper.cn/input/30984380_202506150533eca031eb-9e15-466a-955e-676d35af6b0e.mp3","imgSrc":"https://imgpai.thepaper.cn/newpai/image/1749884402773_xRynrP_1749884403027.png","isHaveVoice":"1"},"softAdTypeStr":"1,1,1","originalContId":30984380,"paywalled":false,"audiovisualBlogSwitch":false,"audiovisualBlogGuests":""},{"contId":"30985315","isOutForword":"0","isOutForward":"0","forwardType":"0","mobForwardType":2,"interactionNum":"59","praiseTimes":"135","pic":"https://imgpai.thepaper.cn/newpai/image/1749912648413_tkMfDK_1749912648636.png","imgCardMode":0,"smallPic":"https://imgpai.thepaper.cn/newpai/image/1749912648413_tkMfDK_1749912648636.png?x-oss-process=image/resize,w_332","sharePic":"https://imgpai.thepaper.cn/newpai/image/1749912648349_3dsYf2_1749912648638.png","pubTime":"19小时前","pubTimeNew":"19小时前","name":"王毅同伊朗外长阿拉格齐通电话","closePraise":"0","nodeInfo":{"nodeId":122905,"name":"大国外交","desc":"构建人类命运共同体","pic":"https://imagecloud.thepaper.cn/thepaper/image/225/728/225.png","nodeType":0,"channelType":0,"forwordType":22,"forwardType":"22","liveType":"2","parentId":25388,"isOrder":"0","dataType":"0","shareName":"大国外交","nickName":"","publishTime":1668726187654,"mobForwardType":"22","summarize":"构建人类命运共同体","color":"","videoLivingRoomDes":"","wwwSpecNodeAlign":0,"govAffairsType":"","showSpecialBanner":false,"showSpecialTopDesc":false,"topBarTypeCustomColor":false,"showVideoBottomRightBtn":false},"nodeId":122905,"contType":0,"pubTimeLong":1749911864955,"specialNodeId":0,"cardMode":"101","dataObjId":52,"closeFrontComment":false,"isSupInteraction":false,"tagList":[{"tagId":6201,"tag":"王毅","isOrder":"0","isUpdateNotify":"0","isWonderfulComments":"0"},{"tagId":4074,"tag":"伊朗","isOrder":"0","isUpdateNotify":"0","isWonderfulComments":"0"},{"tagId":31530,"tag":"中东局势","isOrder":"0","isUpdateNotify":"0","isWonderfulComments":"0"}],"hideVideoFlag":false,"praiseStyle":1,"isSustainedFly":0,"softLocType":1,"closeComment":false,"voiceInfo":{"voiceSrc":"https://audios.thepaper.cn/input/30985315_20250615073336493816-7763-4032-b464-885c6f078fe4.mp3","imgSrc":"https://imgpai.thepaper.cn/newpai/image/1749912648349_3dsYf2_1749912648638.png","isHaveVoice":"1"},"softAdTypeStr":"1,1,1","originalContId":30985315,"paywalled":false,"audiovisualBlogSwitch":false,"audiovisualBlogGuests":""},{"contId":"30984790","isOutForword":"0","isOutForward":"0","forwardType":"0","mobForwardType":2,"interactionNum":"65","praiseTimes":"31","pic":"https://imgpai.thepaper.cn/newpai/image/1749898050416_Dmr1C7_1749898050531.png","imgCardMode":0,"smallPic":"https://imgpai.thepaper.cn/newpai/image/1749898050416_Dmr1C7_1749898050531.png?x-oss-process=image/resize,w_332","sharePic":"https://imgpai.thepaper.cn/newpai/image/1749898050418_prnyx5_1749898050520.png","pubTime":"21小时前","pubTimeNew":"21小时前","name":"探访内测中的上海乐高乐园：亲子家庭是主力，游乐设备仍在“磨合”","closePraise":"0","waterMark":{"type":"4","value":"1","bigPicValue":"1"},"nodeInfo":{"nodeId":25422,"name":"浦江头条","desc":"上海每天最重要的事件","pic":"https://imagecloud.thepaper.cn/thepaper/image/4/158/81.png","nodeType":0,"channelType":0,"forwordType":22,"forwardType":"22","liveType":"1","parentId":25388,"isOrder":"0","dataType":"0","shareName":"浦江头条","nickName":"","mobForwardType":"22","recommendIds":[13851102],"summarize":"不满足于最动态，还要最重要；丰富而不琐碎，快速但不轻浮。你最想关注的上海新闻，这里肯定有，你应该知道的上海新闻，这里也会有。","color":"","videoLivingRoomDes":"","wwwSpecNodeAlign":0,"govAffairsType":"","showSpecialBanner":false,"showSpecialTopDesc":false,"topBarTypeCustomColor":false,"showVideoBottomRightBtn":false},"nodeId":25422,"contType":0,"pubTimeLong":1749907149895,"specialNodeId":0,"cardMode":"101","dataObjId":52,"closeFrontComment":false,"isSupInteraction":false,"tagList":[{"tagId":3335053,"tag":"上海乐高乐园","isOrder":"0","isUpdateNotify":"0","isWonderfulComments":"0"}],"hideVideoFlag":false,"praiseStyle":1,"isSustainedFly":0,"softLocType":1,"closeComment":false,"voiceInfo":{"voiceSrc":"https://audios.thepaper.cn/input/30984790_2025061505331aa6c0a1-cee4-4e45-ade3-dd0f5516fff8.mp3","imgSrc":"https://imgpai.thepaper.cn/newpai/image/1749898050418_prnyx5_1749898050520.png","isHaveVoice":"1"},"softAdTypeStr":"1,1,1","originalContId":30984790,"paywalled":false,"audiovisualBlogSwitch":false,"audiovisualBlogGuests":""},{"contId":"30984803","isOutForword":"0","isOutForward":"0","forwardType":"0","mobForwardType":2,"interactionNum":"47","praiseTimes":"126","pic":"https://imgpai.thepaper.cn/newpai/image/1749898966971_pNrkhJ_1749898967219.png","imgCardMode":0,"smallPic":"https://imgpai.thepaper.cn/newpai/image/1749898966971_pNrkhJ_1749898967219.png?x-oss-process=image/resize,w_332","sharePic":"https://imgpai.thepaper.cn/newpai/image/1749898966972_7ft1JR_1749898967187.png","pubTime":"23小时前","pubTimeNew":"23小时前","name":"女生万象城遭挟持？杭州上城警方通报","closePraise":"0","nodeInfo":{"nodeId":25491,"name":"长三角政商","desc":"解读区域政情与财富故事","pic":"https://imagecloud.thepaper.cn/thepaper/image/4/158/69.png","nodeType":0,"channelType":0,"forwordType":22,"forwardType":"22","liveType":"2","parentId":25388,"isOrder":"0","dataType":"0","shareName":"长三角政商","nickName":"","mobForwardType":"22","summarize":"深耕中国最大都市群，阐释、发微、钩沉“富贵门”里形形色色的政情动向与财富故事，以及这块冲积平原对中国政经情势放射的冲击波。","color":"","videoLivingRoomDes":"","wwwSpecNodeAlign":0,"govAffairsType":"","showSpecialBanner":false,"showSpecialTopDesc":false,"topBarTypeCustomColor":false,"showVideoBottomRightBtn":false},"nodeId":25491,"contType":0,"pubTimeLong":1749899026337,"specialNodeId":0,"cardMode":"101","dataObjId":52,"closeFrontComment":false,"isSupInteraction":false,"tagList":[{"tagId":131596,"tag":"万象城","isOrder":"0","isUpdateNotify":"0","isWonderfulComments":"0"},{"tagId":1793,"tag":"杭州","isOrder":"0","isUpdateNotify":"0","isWonderfulComments":"0"},{"tagId":99099,"tag":"挟持","isOrder":"0","isUpdateNotify":"0","isWonderfulComments":"0"}],"hideVideoFlag":false,"praiseStyle":1,"isSustainedFly":0,"softLocType":1,"closeComment":false,"voiceInfo":{"voiceSrc":"https://audios.thepaper.cn/input/30984803_2025061421336a3ab785-30aa-455f-8429-472d84c63fb5.mp3","imgSrc":"https://imgpai.thepaper.cn/newpai/image/1749898966972_7ft1JR_1749898967187.png","isHaveVoice":"1"},"softAdTypeStr":"1,1,1","originalContId":30984803,"paywalled":false,"audiovisualBlogSwitch":false,"audiovisualBlogGuests":""},{"contId":"30986857","isOutForword":"0","isOutForward":"0","forwardType":"0","mobForwardType":2,"interactionNum":"94","praiseTimes":"62","pic":"https://imgpai.thepaper.cn/newpai/image/1749956861671_FJhCNW_1749956861883.png","imgCardMode":0,"smallPic":"https://imgpai.thepaper.cn/newpai/image/1749956861671_FJhCNW_1749956861883.png?x-oss-process=image/resize,w_332","sharePic":"https://imgpai.thepaper.cn/newpai/image/1749956861676_inaw6t_1749956861867.png","pubTime":"7小时前","pubTimeNew":"7小时前","name":"马英九：两岸人民之间的情感与交流无法中断","closePraise":"0","nodeInfo":{"nodeId":25463,"name":"港台来信","desc":"感觉不一样的港台报道","pic":"https://imagecloud.thepaper.cn/thepaper/image/4/158/68.png","nodeType":0,"channelType":0,"forwordType":22,"forwardType":"22","liveType":"2","parentId":25388,"isOrder":"0","dataType":"0","shareName":"港台来信","nickName":"","mobForwardType":"22","summarize":"港台风云变幻时，我们是华人民主实验瞭望台。民间群情而起时，我们是两地社会情绪探测仪。两岸三地观人及己，在理解中消误解，在欣赏中增互信。","color":"","videoLivingRoomDes":"","wwwSpecNodeAlign":0,"govAffairsType":"","showSpecialBanner":false,"showSpecialTopDesc":false,"topBarTypeCustomColor":false,"showVideoBottomRightBtn":false},"nodeId":25463,"contType":0,"pubTimeLong":1749957794096,"specialNodeId":0,"cardMode":"101","dataObjId":52,"closeFrontComment":false,"isSupInteraction":false,"tagList":[{"tagId":109,"tag":"两岸关系","isOrder":"0","isUpdateNotify":"0","isWonderfulComments":"0"},{"tagId":199,"tag":"马英九","isOrder":"0","isUpdateNotify":"0","isWonderfulComments":"0"},{"tagId":6882305,"tag":"海峡论坛大会","isOrder":"0","isUpdateNotify":"0","isWonderfulComments":"0"}],"hideVideoFlag":false,"praiseStyle":1,"isSustainedFly":0,"softLocType":1,"closeComment":false,"voiceInfo":{"voiceSrc":"https://audios.thepaper.cn/input/30986857_2025061514330a174ba8-039b-4a10-a367-08ccf2bc1367.mp3","imgSrc":"https://imgpai.thepaper.cn/newpai/image/1749956861676_inaw6t_1749956861867.png","isHaveVoice":"1"},"softAdTypeStr":"1,1,1","originalContId":30986857,"paywalled":false,"audiovisualBlogSwitch":false,"audiovisualBlogGuests":""},{"contId":"30985314","isOutForword":"0","isOutForward":"0","forwardType":"0","mobForwardType":2,"interactionNum":"37","praiseTimes":"615","pic":"https://imgpai.thepaper.cn/newpai/image/1749940082390_RPEYhC_1749940082678.png","imgCardMode":0,"smallPic":"https://imgpai.thepaper.cn/newpai/image/1749940082390_RPEYhC_1749940082678.png?x-oss-process=image/resize,w_332","sharePic":"https://imgpai.thepaper.cn/newpai/image/1749940082393_DeZ7cF_1749940082666.png","pubTime":"10小时前","pubTimeNew":"10小时前","name":"上海乐高乐园探营：安检不“翻包”，超8500万块积木演绎乐高世界的“情景剧”","closePraise":"0","nodeInfo":{"nodeId":25433,"name":"地产界","desc":"地产界所有你想知道的事儿","pic":"https://imagecloud.thepaper.cn/thepaper/image/4/158/86.png","nodeType":0,"channelType":0,"forwordType":22,"forwardType":"22","liveType":"1","parentId":25388,"isOrder":"0","dataType":"0","shareName":"地产界","nickName":"","mobForwardType":"22","summarize":"提供地产界最新的投资趋势、最热的地区规划、最深入的政策解读。","color":"","videoLivingRoomDes":"","wwwSpecNodeAlign":0,"govAffairsType":"","showSpecialBanner":false,"showSpecialTopDesc":false,"topBarTypeCustomColor":false,"showVideoBottomRightBtn":false},"nodeId":25433,"contType":0,"pubTimeLong":1749945868957,"specialNodeId":0,"cardMode":"101","dataObjId":52,"closeFrontComment":false,"isSupInteraction":false,"tagList":[{"tagId":3335053,"tag":"上海乐高乐园","isOrder":"0","isUpdateNotify":"0","isWonderfulComments":"0"},{"tagId":3066921,"tag":"上海乐高乐园度假区","isOrder":"0","isUpdateNotify":"0","isWonderfulComments":"0"},{"tagId":93473,"tag":"乐高","isOrder":"0","isUpdateNotify":"0","isWonderfulComments":"0"},{"tagId":211817,"tag":"乐高乐园","isOrder":"0","isUpdateNotify":"0","isWonderfulComments":"0"},{"tagId":6854247,"tag":"乐高乐园酒店","isOrder":"0","isUpdateNotify":"0","isWonderfulComments":"0"}],"hideVideoFlag":false,"praiseStyle":1,"isSustainedFly":0,"softLocType":1,"closeComment":false,"voiceInfo":{"voiceSrc":"https://audios.thepaper.cn/input/30985314_202506151133891827f7-541e-4eb1-87fb-110fed6a25cd.mp3","imgSrc":"https://imgpai.thepaper.cn/newpai/image/1749940082393_DeZ7cF_1749940082666.png","isHaveVoice":"1"},"softAdTypeStr":"1,1,1","originalContId":30985314,"paywalled":false,"audiovisualBlogSwitch":false,"audiovisualBlogGuests":""},{"contId":"30986586","isOutForword":"0","isOutForward":"0","forwardType":"0","mobForwardType":2,"interactionNum":"185","praiseTimes":"219","pic":"https://imgpai.thepaper.cn/newpai/image/1749944782836_Nwbn74_1749944783085.png","imgCardMode":0,"smallPic":"https://imgpai.thepaper.cn/newpai/image/1749944782836_Nwbn74_1749944783085.png?x-oss-process=image/resize,w_332","sharePic":"https://imgpai.thepaper.cn/newpai/image/1749944782841_8XBS57_1749944783055.png","pubTime":"10小时前","pubTimeNew":"10小时前","name":"“价格战”愈演愈烈、车企集体发声反对“内卷式”竞争，如何重回正常市场环境？","closePraise":"0","nodeInfo":{"nodeId":25434,"name":"10%公司","desc":"派发上市公司变革红利","pic":"https://imagecloud.thepaper.cn/thepaper/image/4/158/87.png","nodeType":0,"channelType":0,"forwordType":22,"forwardType":"22","liveType":"1","parentId":25388,"isOrder":"0","dataType":"0","shareName":"10%公司","nickName":"","mobForwardType":"22","summarize":"聚焦公司变革，致力于发现10%最优质公司。","color":"","videoLivingRoomDes":"","wwwSpecNodeAlign":0,"govAffairsType":"","showSpecialBanner":false,"showSpecialTopDesc":false,"topBarTypeCustomColor":false,"showVideoBottomRightBtn":false},"nodeId":25434,"contType":0,"pubTimeLong":1749945001865,"specialNodeId":0,"cardMode":"101","dataObjId":52,"closeFrontComment":false,"isSupInteraction":false,"tagList":[{"tagId":6882378,"tag":"车企内卷","isOrder":"0","isUpdateNotify":"0","isWonderfulComments":"0"}],"hideVideoFlag":false,"praiseStyle":1,"isSustainedFly":0,"softLocType":1,"closeComment":false,"voiceInfo":{"voiceSrc":"https://audios.thepaper.cn/input/30986586_20250615113315961226-9e97-4ba2-8e6d-14c75bc420db.mp3","imgSrc":"https://imgpai.thepaper.cn/newpai/image/1749944782841_8XBS57_1749944783055.png","isHaveVoice":"1"},"softAdTypeStr":"1,1,1","originalContId":30986586,"paywalled":false,"audiovisualBlogSwitch":false,"audiovisualBlogGuests":""},{"contId":"30986901","isOutForword":"0","isOutForward":"0","forwardType":"0","mobForwardType":2,"interactionNum":"69","praiseTimes":"151","pic":"https://imgpai.thepaper.cn/newpai/image/1749958365375_azCT8B_1749958365608.png","imgCardMode":0,"smallPic":"https://imgpai.thepaper.cn/newpai/image/1749958365375_azCT8B_1749958365608.png?x-oss-process=image/resize,w_332","sharePic":"https://imgpai.thepaper.cn/newpai/image/1749958365417_tHz6Fj_1749958365628.png","pubTime":"7小时前","pubTimeNew":"7小时前","name":"李在明纪念《北南共同宣言》发表25周年，再提恢复韩朝对话合作","closePraise":"0","nodeInfo":{"nodeId":25429,"name":"全球速报","desc":"最热点的全球资讯","pic":"https://imagecloud.thepaper.cn/thepaper/image/4/158/73.png","nodeType":0,"channelType":0,"forwordType":22,"forwardType":"22","liveType":"2","parentId":25388,"isOrder":"0","dataType":"0","shareName":"全球速报","nickName":"","publishTime":1668726066292,"mobForwardType":"22","summarize":"最热点的全球资讯","color":"","videoLivingRoomDes":"","wwwSpecNodeAlign":0,"govAffairsType":"","showSpecialBanner":false,"showSpecialTopDesc":false,"topBarTypeCustomColor":false,"showVideoBottomRightBtn":false},"nodeId":25429,"contType":0,"pubTimeLong":1749958309366,"specialNodeId":0,"cardMode":"101","dataObjId":52,"closeFrontComment":false,"isSupInteraction":false,"tagList":[{"tagId":2833045,"tag":"李在明","isOrder":"0","isUpdateNotify":"0","isWonderfulComments":"0"},{"tagId":806609,"tag":"韩朝对话","isOrder":"0","isUpdateNotify":"0","isWonderfulComments":"0"}],"hideVideoFlag":false,"praiseStyle":1,"isSustainedFly":0,"softLocType":1,"closeComment":false,"voiceInfo":{"voiceSrc":"https://audios.thepaper.cn/input/30986901_202506151233c5b35046-6bf1-489c-af00-649f5012c3df.mp3","imgSrc":"https://imgpai.thepaper.cn/newpai/image/1749958365417_tHz6Fj_1749958365628.png","isHaveVoice":"1"},"softAdTypeStr":"1,1,1","originalContId":30986901,"paywalled":false,"audiovisualBlogSwitch":false,"audiovisualBlogGuests":""},{"contId":"30985343","isOutForword":"0","isOutForward":"0","forwardType":"0","mobForwardType":2,"interactionNum":"37","praiseTimes":"81","pic":"https://imgpai.thepaper.cn/newpai/image/1749913451766_EdSeFQ_1749913452114.png","imgCardMode":0,"smallPic":"https://imgpai.thepaper.cn/newpai/image/1749913451766_EdSeFQ_1749913452114.png?x-oss-process=image/resize,w_332","sharePic":"https://imgpai.thepaper.cn/newpai/image/1749913451840_4bzMnG_1749913452125.png","pubTime":"19小时前","pubTimeNew":"19小时前","name":"王毅同以色列外长萨尔通电话","closePraise":"0","nodeInfo":{"nodeId":122905,"name":"大国外交","desc":"构建人类命运共同体","pic":"https://imagecloud.thepaper.cn/thepaper/image/225/728/225.png","nodeType":0,"channelType":0,"forwordType":22,"forwardType":"22","liveType":"2","parentId":25388,"isOrder":"0","dataType":"0","shareName":"大国外交","nickName":"","publishTime":1668726187654,"mobForwardType":"22","summarize":"构建人类命运共同体","color":"","videoLivingRoomDes":"","wwwSpecNodeAlign":0,"govAffairsType":"","showSpecialBanner":false,"showSpecialTopDesc":false,"topBarTypeCustomColor":false,"showVideoBottomRightBtn":false},"nodeId":122905,"contType":0,"pubTimeLong":1749912885714,"specialNodeId":0,"cardMode":"101","dataObjId":52,"closeFrontComment":false,"isSupInteraction":false,"tagList":[{"tagId":6201,"tag":"王毅","isOrder":"0","isUpdateNotify":"0","isWonderfulComments":"0"}],"hideVideoFlag":false,"praiseStyle":1,"isSustainedFly":0,"softLocType":1,"closeComment":false,"voiceInfo":{"voiceSrc":"https://audios.thepaper.cn/input/30985343_20250615153385f0dc8f-f25f-4628-89e3-a7ddbcc0bb5f.mp3","imgSrc":"https://imgpai.thepaper.cn/newpai/image/1749913451840_4bzMnG_1749913452125.png","isHaveVoice":"1"},"softAdTypeStr":"1,1,1","originalContId":30985343,"paywalled":false,"audiovisualBlogSwitch":false,"audiovisualBlogGuests":""},{"contId":"30984919","isOutForword":"0","isOutForward":"0","forwardType":"0","mobForwardType":2,"interactionNum":"75","praiseTimes":"183","pic":"https://imgpai.thepaper.cn/newpai/image/1749903273425_H4CNiX_1749903273599.png","imgCardMode":0,"smallPic":"https://imgpai.thepaper.cn/newpai/image/1749903273425_H4CNiX_1749903273599.png?x-oss-process=image/resize,w_332","sharePic":"https://imgpai.thepaper.cn/newpai/image/1749903273428_NDe3tD_1749903273666.png","pubTime":"11小时前","pubTimeNew":"11小时前","name":"技术派｜伊朗导弹密集打击以色列，高超声速导弹表现令人瞩目","closePraise":"0","nodeInfo":{"nodeId":25430,"name":"澎湃防务","desc":"传递最新鲜、专业的全球防务新闻，探析军事发展趋势","pic":"https://imagecloud.thepaper.cn/thepaper/image/4/158/77.png","nodeType":0,"channelType":0,"forwordType":22,"forwardType":"22","liveType":"2","parentId":25388,"isOrder":"0","dataType":"0","shareName":"澎湃防务","nickName":"","publishTime":1708421052562,"mobForwardType":"22","summarize":"通过新媒体多元的表达方式，向读者传递最新鲜、专业的全球防务新闻，探析军事发展趋势。","color":"","videoLivingRoomDes":"","wwwSpecNodeAlign":0,"govAffairsType":"","showSpecialBanner":false,"showSpecialTopDesc":false,"topBarTypeCustomColor":false,"showVideoBottomRightBtn":false},"nodeId":25430,"contType":0,"pubTimeLong":1749943420887,"specialNodeId":0,"cardMode":"101","dataObjId":52,"closeFrontComment":false,"isSupInteraction":false,"tagList":[{"tagId":6108752,"tag":"伊朗打击以色列","isOrder":"0","isUpdateNotify":"0","isWonderfulComments":"0"}],"hideVideoFlag":false,"praiseStyle":1,"isSustainedFly":0,"softLocType":1,"closeComment":false,"voiceInfo":{"voiceSrc":"https://audios.thepaper.cn/input/30984919_20250615093387451ede-da65-4b1f-bdcf-84236a32a491.mp3","imgSrc":"https://imgpai.thepaper.cn/newpai/image/1749903273428_NDe3tD_1749903273666.png","isHaveVoice":"1"},"softAdTypeStr":"1,1,1","originalContId":30984919,"paywalled":false,"audiovisualBlogSwitch":false,"audiovisualBlogGuests":""},{"contId":"30986611","isOutForword":"0","isOutForward":"0","forwardType":"0","mobForwardType":2,"interactionNum":"81","praiseTimes":"142","pic":"https://imgpai.thepaper.cn/newpai/image/1749947473839_dKbh6b_1749947474071.png","imgCardMode":0,"smallPic":"https://imgpai.thepaper.cn/newpai/image/1749947473839_dKbh6b_1749947474071.png?x-oss-process=image/resize,w_332","sharePic":"https://imgpai.thepaper.cn/newpai/image/1749947473844_sN81NZ_1749947474046.png","pubTime":"8小时前","pubTimeNew":"8小时前","name":"供水公司换智能水表要求预存200元水费，被指“滥用市场支配地位”","closePraise":"0","nodeInfo":{"nodeId":25464,"name":"澎湃质量观","desc":"打假除劣，破套防坑——专注消费者权益保护","pic":"https://imagecloud.thepaper.cn/thepaper/image/7/608/930.jpg","nodeType":0,"channelType":0,"forwordType":22,"forwardType":"22","liveType":"2","parentId":25388,"isOrder":"0","dataType":"0","shareName":"澎湃质量观","nickName":"","mobForwardType":"22","summarize":"打假除劣，破套防坑——专注消费者权益保护。","color":"","videoLivingRoomDes":"","wwwSpecNodeAlign":0,"govAffairsType":"","showSpecialBanner":false,"showSpecialTopDesc":false,"topBarTypeCustomColor":false,"showVideoBottomRightBtn":false},"nodeId":25464,"contType":0,"pubTimeLong":1749951915126,"specialNodeId":0,"cardMode":"101","dataObjId":52,"closeFrontComment":false,"isSupInteraction":false,"tagList":[{"tagId":51254,"tag":"聊城","isOrder":"0","isUpdateNotify":"0","isWonderfulComments":"0"},{"tagId":60075,"tag":"供水","isOrder":"0","isUpdateNotify":"0","isWonderfulComments":"0"},{"tagId":1684,"tag":"水","isOrder":"0","isUpdateNotify":"0","isWonderfulComments":"0"},{"tagId":6882608,"tag":"智能水表更换","isOrder":"0","isUpdateNotify":"0","isWonderfulComments":"0"}],"hideVideoFlag":false,"praiseStyle":1,"isSustainedFly":0,"softLocType":1,"closeComment":false,"voiceInfo":{"voiceSrc":"https://audios.thepaper.cn/input/30986611_202506151233c33c52cd-aabe-4f7c-b761-8fa141edb637.mp3","imgSrc":"https://imgpai.thepaper.cn/newpai/image/1749947473844_sN81NZ_1749947474046.png","isHaveVoice":"1"},"softAdTypeStr":"1,1,1","originalContId":30986611,"paywalled":false,"audiovisualBlogSwitch":false,"audiovisualBlogGuests":""},{"contId":"30987362","isOutForword":"0","isOutForward":"0","forwardType":"0","mobForwardType":2,"interactionNum":"47","praiseTimes":"103","pic":"https://imgpai.thepaper.cn/newpai/image/1749970635955_txf315_1749970636176.png","imgCardMode":0,"smallPic":"https://imgpai.thepaper.cn/newpai/image/1749970635955_txf315_1749970636176.png?x-oss-process=image/resize,w_332","sharePic":"https://imgpai.thepaper.cn/newpai/image/1749970636001_8G2HE1_1749970636308.png","pubTime":"3小时前","pubTimeNew":"3小时前","name":"中传公布优秀毕业生去向：建党百年庆典领诵团成员沈倩拟入职新华社","closePraise":"0","nodeInfo":{"nodeId":25487,"name":"教育家","desc":"最先进的教育理念在此碰撞","pic":"https://imagecloud.thepaper.cn/thepaper/image/4/158/83.png","nodeType":0,"channelType":0,"forwordType":22,"forwardType":"22","liveType":"2","parentId":25388,"isOrder":"0","dataType":"0","shareName":"教育家","nickName":"","mobForwardType":"22","summarize":"聚焦教育发展，剖析改革难题，将最前沿的教育理念与所有人分享。每个人都是教育家，只等你拿出真知灼见。","color":"","videoLivingRoomDes":"","wwwSpecNodeAlign":0,"govAffairsType":"","showSpecialBanner":false,"showSpecialTopDesc":false,"topBarTypeCustomColor":false,"showVideoBottomRightBtn":false},"nodeId":25487,"contType":0,"pubTimeLong":1749972071036,"specialNodeId":0,"cardMode":"101","dataObjId":52,"closeFrontComment":false,"isSupInteraction":false,"tagList":[{"tagId":380505,"tag":"中传","isOrder":"0","isUpdateNotify":"0","isWonderfulComments":"0"}],"hideVideoFlag":false,"praiseStyle":1,"isSustainedFly":0,"softLocType":1,"closeComment":false,"voiceInfo":{"voiceSrc":"https://audios.thepaper.cn/input/30987362_2025061518338e1ffe32-ca6a-4205-bc4c-5b8c7b6c7429.mp3","imgSrc":"https://imgpai.thepaper.cn/newpai/image/1749970636001_8G2HE1_1749970636308.png","isHaveVoice":"1"},"softAdTypeStr":"1,1,1","originalContId":30987362,"paywalled":false,"audiovisualBlogSwitch":false,"audiovisualBlogGuests":""},{"contId":"30984800","isOutForword":"0","isOutForward":"0","forwardType":"74","mobForwardType":74,"interactionNum":"37","praiseTimes":"188","pic":"https://imgpai.thepaper.cn/newpai/image/1749898214295_e46x4C_1749898214447.png","imgCardMode":0,"smallPic":"https://imgpai.thepaper.cn/newpai/image/1749898214295_e46x4C_1749898214447.png?x-oss-process=image/resize,w_332","sharePic":"https://imgpai.thepaper.cn/newpai/image/1749898214332_CQJcNC_1749898214658.png","pubTime":"22小时前","pubTimeNew":"22小时前","name":"北京多所高校禁用罗马仕充电宝","closePraise":"0","waterMark":{"type":"1","value":"00:49","bigPicValue":"00:49","videoSize":"4M流量"},"nodeInfo":{"nodeId":26913,"name":"锋线视频","desc":"不满足于琐碎的片段，做有态度的新闻视频。","pic":"https://imagecloud.thepaper.cn/thepaper/image/340/125/528.png","nodeType":4,"channelType":0,"forwordType":22,"forwardType":"23","liveType":"2","parentId":26886,"isOrder":"0","dataType":"0","shareName":"锋线视频","nickName":"","publishTime":1739242842669,"mobForwardType":"23","summarize":"不满足于琐碎的片段，做有态度的新闻视频。","color":"","videoLivingRoomDes":"","wwwSpecNodeAlign":0,"govAffairsType":"","showSpecialBanner":false,"showSpecialTopDesc":false,"topBarTypeCustomColor":false,"showVideoBottomRightBtn":false},"videos":{"videoId":null,"hdurl":"https://cloudvideo.thepaper.cn/video/91157e1d06814a05b145409c3c046415/hd/1749901980375_aTzJcx_1749902047005.mp4","url":"https://cloudvideo.thepaper.cn/video/91157e1d06814a05b145409c3c046415/sd/1749901980375_aTzJcx_1749902047005.mp4","duration":"00:49","coverUrl":"https://imgpai.thepaper.cn/newpai/image/1749897345000_2mnhAe_1749902046043.jpg","verticalCoverUrl":"https://imgpai.thepaper.cn/newpai/image/1749898214330_xxY6KB_1749898214662.png","bytes":"7548503","hdBytes":"13898856","coverUrlFirstFrame":"http://cloudvideo.thepaper.cn/video/91157e1d06814a05b145409c3c046415/1000.jpg","verticalVideo":true,"durationNum":49,"videoDes":null,"playInfos":null,"outLink":false},"nodeId":26913,"contType":9,"pubTimeLong":1749904430076,"specialNodeId":0,"cardMode":"101","dataObjId":52,"closeFrontComment":false,"isSupInteraction":false,"tagList":[{"tagId":6882178,"tag":"罗马仕充电宝","isOrder":"0","isUpdateNotify":"0","isWonderfulComments":"0"}],"hideVideoFlag":false,"praiseStyle":1,"isSustainedFly":0,"softLocType":1,"closeComment":false,"voiceInfo":{"voiceSrc":"https://audios.thepaper.cn/input/30984800_202506151333b45b395c-7c47-433b-9090-1256a53d5422.mp3","imgSrc":"https://imgpai.thepaper.cn/newpai/image/1749898214332_CQJcNC_1749898214658.png","isHaveVoice":"1"},"softAdTypeStr":"1,1,1","originalContId":30984800,"paywalled":false,"audiovisualBlogSwitch":false,"audiovisualBlogGuests":""},{"contId":"30985349","isOutForword":"0","isOutForward":"0","forwardType":"0","mobForwardType":2,"interactionNum":"59","praiseTimes":"105","pic":"https://imgpai.thepaper.cn/newpai/image/1749918972115_A1fJCE_1749918972578.png","imgCardMode":0,"smallPic":"https://imgpai.thepaper.cn/newpai/image/1749918972115_A1fJCE_1749918972578.png?x-oss-process=image/resize,w_332","sharePic":"https://imgpai.thepaper.cn/newpai/image/1749918972189_ZPA44K_1749918972588.png","pubTime":"17小时前","pubTimeNew":"17小时前","name":"俄美总统再次通话，普京透露俄准备调解伊以冲突","closePraise":"0","nodeInfo":{"nodeId":25429,"name":"全球速报","desc":"最热点的全球资讯","pic":"https://imagecloud.thepaper.cn/thepaper/image/4/158/73.png","nodeType":0,"channelType":0,"forwordType":22,"forwardType":"22","liveType":"2","parentId":25388,"isOrder":"0","dataType":"0","shareName":"全球速报","nickName":"","publishTime":1668726066292,"mobForwardType":"22","summarize":"最热点的全球资讯","color":"","videoLivingRoomDes":"","wwwSpecNodeAlign":0,"govAffairsType":"","showSpecialBanner":false,"showSpecialTopDesc":false,"topBarTypeCustomColor":false,"showVideoBottomRightBtn":false},"nodeId":25429,"contType":0,"pubTimeLong":1749918890580,"specialNodeId":0,"cardMode":"101","dataObjId":52,"closeFrontComment":false,"isSupInteraction":false,"tagList":[{"tagId":408,"tag":"俄罗斯","isOrder":"0","isUpdateNotify":"0","isWonderfulComments":"0"},{"tagId":33,"tag":"美国","isOrder":"0","isUpdateNotify":"0","isWonderfulComments":"0"}],"hideVideoFlag":false,"praiseStyle":1,"isSustainedFly":0,"softLocType":1,"closeComment":false,"voiceInfo":{"voiceSrc":"https://audios.thepaper.cn/input/30985349_20250615103379c36362-826b-47a8-bdd9-129cc2d4adb1.mp3","imgSrc":"https://imgpai.thepaper.cn/newpai/image/1749918972189_ZPA44K_1749918972588.png","isHaveVoice":"1"},"softAdTypeStr":"1,1,1","originalContId":30985349,"paywalled":false,"audiovisualBlogSwitch":false,"audiovisualBlogGuests":""},{"contId":"30986775","isOutForword":"0","isOutForward":"0","forwardType":"74","mobForwardType":74,"interactionNum":"194","praiseTimes":"47","pic":"https://imgpai.thepaper.cn/newpai/image/1749951748236_k7Nafz_1749951748636.png","imgCardMode":0,"smallPic":"https://imgpai.thepaper.cn/newpai/image/1749951748236_k7Nafz_1749951748636.png?x-oss-process=image/resize,w_332","sharePic":"https://imgpai.thepaper.cn/newpai/image/1749951748237_7mXA4W_1749951748541.png","pubTime":"8小时前","pubTimeNew":"8小时前","name":"重庆警方：男子持续鸣笛引发路人不满，强行驾车驶离致1死4伤","closePraise":"0","waterMark":{"type":"1","value":"00:23","bigPicValue":"00:23","videoSize":"1M流量"},"nodeInfo":{"nodeId":26913,"name":"锋线视频","desc":"不满足于琐碎的片段，做有态度的新闻视频。","pic":"https://imagecloud.thepaper.cn/thepaper/image/340/125/528.png","nodeType":4,"channelType":0,"forwordType":22,"forwardType":"23","liveType":"2","parentId":26886,"isOrder":"0","dataType":"0","shareName":"锋线视频","nickName":"","publishTime":1739242842669,"mobForwardType":"23","summarize":"不满足于琐碎的片段，做有态度的新闻视频。","color":"","videoLivingRoomDes":"","wwwSpecNodeAlign":0,"govAffairsType":"","showSpecialBanner":false,"showSpecialTopDesc":false,"topBarTypeCustomColor":false,"showVideoBottomRightBtn":false},"videos":{"videoId":null,"hdurl":"https://cloudvideo.thepaper.cn/video/8b5ca0a0103242a896cd780e0ecd7a61/hd/1749951133717_2mX1kZ_1749951605046.mp4","url":"https://cloudvideo.thepaper.cn/video/8b5ca0a0103242a896cd780e0ecd7a61/sd/1749951133717_2mX1kZ_1749951605046.mp4","duration":"00:23","coverUrl":"https://imgpai.thepaper.cn/newpai/image/1749951603345_3jS7XW_1749951603499.png","verticalCoverUrl":"https://imgpai.thepaper.cn/newpai/image/1749951748237_mFPEYr_1749951748529.png","bytes":"1817831","hdBytes":"4015623","coverUrlFirstFrame":"http://cloudvideo.thepaper.cn/video/8b5ca0a0103242a896cd780e0ecd7a61/1000.jpg","verticalVideo":true,"durationNum":23,"videoDes":null,"playInfos":null,"outLink":false},"nodeId":26913,"contType":9,"pubTimeLong":1749954088995,"specialNodeId":0,"cardMode":"101","dataObjId":52,"closeFrontComment":false,"isSupInteraction":false,"tagList":[{"tagId":6882668,"tag":"持续鸣笛","isOrder":"0","isUpdateNotify":"0","isWonderfulComments":"0"}],"hideVideoFlag":false,"praiseStyle":1,"isSustainedFly":0,"softLocType":1,"closeComment":false,"voiceInfo":{"voiceSrc":"https://audios.thepaper.cn/input/30986775_202506151533e0926248-304d-4aaf-abd2-1e1406471eb4.mp3","imgSrc":"https://imgpai.thepaper.cn/newpai/image/1749951748237_7mXA4W_1749951748541.png","isHaveVoice":"1"},"softAdTypeStr":"1,1,1","originalContId":30986775,"paywalled":false,"audiovisualBlogSwitch":false,"audiovisualBlogGuests":""},{"contId":"30984921","isOutForword":"0","isOutForward":"0","forwardType":"0","mobForwardType":2,"interactionNum":"25","praiseTimes":"159","pic":"https://imgpai.thepaper.cn/newpai/image/1749902974021_iHA67K_1749902974280.png","imgCardMode":0,"smallPic":"https://imgpai.thepaper.cn/newpai/image/1749902974021_iHA67K_1749902974280.png?x-oss-process=image/resize,w_332","sharePic":"https://imgpai.thepaper.cn/newpai/image/1749902974025_Ajd53z_1749902974283.png","pubTime":"22小时前","pubTimeNew":"22小时前","name":"到任第二天，同济大学校长杨金龙与毕业生谈起“如何坚持长期主义”","closePraise":"0","nodeInfo":{"nodeId":25422,"name":"浦江头条","desc":"上海每天最重要的事件","pic":"https://imagecloud.thepaper.cn/thepaper/image/4/158/81.png","nodeType":0,"channelType":0,"forwordType":22,"forwardType":"22","liveType":"1","parentId":25388,"isOrder":"0","dataType":"0","shareName":"浦江头条","nickName":"","mobForwardType":"22","recommendIds":[13851102],"summarize":"不满足于最动态，还要最重要；丰富而不琐碎，快速但不轻浮。你最想关注的上海新闻，这里肯定有，你应该知道的上海新闻，这里也会有。","color":"","videoLivingRoomDes":"","wwwSpecNodeAlign":0,"govAffairsType":"","showSpecialBanner":false,"showSpecialTopDesc":false,"topBarTypeCustomColor":false,"showVideoBottomRightBtn":false},"nodeId":25422,"contType":0,"pubTimeLong":1749904249573,"specialNodeId":0,"cardMode":"101","dataObjId":52,"closeFrontComment":false,"isSupInteraction":false,"tagList":[{"tagId":26231,"tag":"同济大学","isOrder":"0","isUpdateNotify":"0","isWonderfulComments":"0"}],"hideVideoFlag":false,"praiseStyle":1,"isSustainedFly":0,"softLocType":1,"closeComment":false,"voiceInfo":{"voiceSrc":"https://audios.thepaper.cn/input/30984921_2025061505330930c020-f352-4b84-8e11-92f956802596.mp3","imgSrc":"https://imgpai.thepaper.cn/newpai/image/1749902974025_Ajd53z_1749902974283.png","isHaveVoice":"1"},"softAdTypeStr":"1,1,1","originalContId":30984921,"paywalled":false,"audiovisualBlogSwitch":false,"audiovisualBlogGuests":""},{"contId":"30979480","isOutForword":"0","isOutForward":"0","forwardType":"0","mobForwardType":2,"interactionNum":"25","praiseTimes":"1043","pic":"https://imgpai.thepaper.cn/newpai/image/1749831223307_Q24BHj_1749831272304.jpg","imgCardMode":0,"smallPic":"https://imgpai.thepaper.cn/newpai/image/1749831223307_Q24BHj_1749831272304.jpg?x-oss-process=image/resize,w_332","sharePic":"https://imgpai.thepaper.cn/newpai/image/1749824826310_dYe1yj_1749824826546.png","pubTime":"10小时前","pubTimeNew":"10小时前","name":"父亲节｜来自父亲","closePraise":"0","nodeInfo":{"nodeId":97313,"name":"海平面","desc":"远，不止于平面","pic":"https://imagecloud.thepaper.cn/thepaper/image/77/321/958.png","nodeType":0,"channelType":0,"forwordType":22,"forwardType":"22","liveType":"1","parentId":25388,"isOrder":"0","dataType":"0","shareName":"海平面","nickName":"","publishTime":1594539503293,"mobForwardType":"22","summarize":"远，不止于平面","color":"","videoLivingRoomDes":"","wwwSpecNodeAlign":0,"govAffairsType":"","showSpecialBanner":false,"showSpecialTopDesc":false,"topBarTypeCustomColor":false,"showVideoBottomRightBtn":false},"nodeId":97313,"contType":0,"pubTimeLong":1749945637101,"specialNodeId":0,"cardMode":"101","dataObjId":52,"closeFrontComment":false,"isSupInteraction":false,"tagList":[{"tagId":7549,"tag":"父亲节","isOrder":"0","isUpdateNotify":"0","isWonderfulComments":"0"},{"tagId":2221899,"tag":"澎湃海报","isOrder":"0","isUpdateNotify":"0","isWonderfulComments":"0"}],"hideVideoFlag":false,"praiseStyle":1,"isSustainedFly":0,"softLocType":1,"closeComment":false,"voiceInfo":{"voiceSrc":"https://audios.thepaper.cn/input/30979480_202506151833d1cd7198-6306-4c0a-9d51-f8dad619d7ed.mp3","imgSrc":"https://imgpai.thepaper.cn/newpai/image/1749824826310_dYe1yj_1749824826546.png","isHaveVoice":"1"},"softAdTypeStr":"1,1,1","originalContId":30979480,"paywalled":false,"audiovisualBlogSwitch":false,"audiovisualBlogGuests":""},{"contId":"30984880","isOutForword":"0","isOutForward":"0","forwardType":"0","mobForwardType":2,"interactionNum":"15","praiseTimes":"6","pic":"https://imgpai.thepaper.cn/newpai/image/1749901160347_Qwz5zh_1749901160648.png","imgCardMode":0,"smallPic":"https://imgpai.thepaper.cn/newpai/image/1749901160347_Qwz5zh_1749901160648.png?x-oss-process=image/resize,w_332","sharePic":"https://imgpai.thepaper.cn/newpai/image/1749901160350_tethej_1749901160514.png","pubTime":"22小时前","pubTimeNew":"22小时前","name":"空难后印度民航部首次记者会：黑匣子已找到，全面检查波音787","closePraise":"0","nodeInfo":{"nodeId":25429,"name":"全球速报","desc":"最热点的全球资讯","pic":"https://imagecloud.thepaper.cn/thepaper/image/4/158/73.png","nodeType":0,"channelType":0,"forwordType":22,"forwardType":"22","liveType":"2","parentId":25388,"isOrder":"0","dataType":"0","shareName":"全球速报","nickName":"","publishTime":1668726066292,"mobForwardType":"22","summarize":"最热点的全球资讯","color":"","videoLivingRoomDes":"","wwwSpecNodeAlign":0,"govAffairsType":"","showSpecialBanner":false,"showSpecialTopDesc":false,"topBarTypeCustomColor":false,"showVideoBottomRightBtn":false},"nodeId":25429,"contType":0,"pubTimeLong":1749902865884,"specialNodeId":0,"cardMode":"101","dataObjId":52,"closeFrontComment":false,"isSupInteraction":false,"tagList":[{"tagId":2144,"tag":"印度","isOrder":"0","isUpdateNotify":"0","isWonderfulComments":"0"},{"tagId":14064,"tag":"坠机","isOrder":"0","isUpdateNotify":"0","isWonderfulComments":"0"},{"tagId":8592,"tag":"波音","isOrder":"0","isUpdateNotify":"0","isWonderfulComments":"0"}],"hideVideoFlag":false,"praiseStyle":1,"isSustainedFly":0,"softLocType":1,"closeComment":false,"voiceInfo":{"voiceSrc":"https://audios.thepaper.cn/input/30984880_202506150833a2d2a5cf-e28e-40e5-b3e2-a4f3d0e21994.mp3","imgSrc":"https://imgpai.thepaper.cn/newpai/image/1749901160350_tethej_1749901160514.png","isHaveVoice":"1"},"softAdTypeStr":"1,1,1","originalContId":30984880,"paywalled":false,"audiovisualBlogSwitch":false,"audiovisualBlogGuests":""},{"contId":"30985318","isOutForword":"0","isOutForward":"0","forwardType":"0","mobForwardType":2,"interactionNum":"21","praiseTimes":"18","pic":"https://imgpai.thepaper.cn/newpai/image/1749912107342_kBfMcZ_1749912107856.png","imgCardMode":0,"smallPic":"https://imgpai.thepaper.cn/newpai/image/1749912107342_kBfMcZ_1749912107856.png?x-oss-process=image/resize,w_332","sharePic":"https://imgpai.thepaper.cn/newpai/image/1749912107353_D7Hjrc_1749912107864.png","pubTime":"19小时前","pubTimeNew":"19小时前","name":"120年的光影之约，全球影人在“电影之城”共同表白电影","closePraise":"0","waterMark":{"type":"4","value":"1","bigPicValue":"1"},"nodeInfo":{"nodeId":25448,"name":"有戏","desc":"陪你过一种审美的生活","pic":"https://imagecloud.thepaper.cn/thepaper/image/4/158/109.png","nodeType":0,"channelType":0,"forwordType":22,"forwardType":"22","liveType":"2","parentId":25389,"isOrder":"0","dataType":"0","shareName":"有戏","nickName":"","mobForwardType":"22","summarize":"告诉你好看的影视、戏剧和演出，陪你过一种审美的生活。","color":"","videoLivingRoomDes":"","wwwSpecNodeAlign":0,"govAffairsType":"","showSpecialBanner":false,"showSpecialTopDesc":false,"topBarTypeCustomColor":false,"showVideoBottomRightBtn":false},"nodeId":25448,"contType":0,"pubTimeLong":1749912953435,"specialNodeId":0,"cardMode":"101","dataObjId":52,"closeFrontComment":false,"isSupInteraction":false,"tagList":[{"tagId":4597,"tag":"上海国际电影节","isOrder":"0","isUpdateNotify":"0","isWonderfulComments":"0"},{"tagId":6881988,"tag":"金爵红毯","isOrder":"0","isUpdateNotify":"0","isWonderfulComments":"0"},{"tagId":6882241,"tag":"酱园弄悬案","isOrder":"0","isUpdateNotify":"0","isWonderfulComments":"0"}],"hideVideoFlag":false,"praiseStyle":1,"isSustainedFly":0,"softLocType":1,"closeComment":false,"voiceInfo":{"voiceSrc":"https://audios.thepaper.cn/input/30985318_2025061518335a6b63b3-942d-4dd8-a417-d772ed0292b1.mp3","imgSrc":"https://imgpai.thepaper.cn/newpai/image/1749912107353_D7Hjrc_1749912107864.png","isHaveVoice":"1"},"softAdTypeStr":"1,1,1","originalContId":30985318,"paywalled":false,"audiovisualBlogSwitch":false,"audiovisualBlogGuests":""}],"editorHandpicked":[{"contId":"30987713","isOutForword":"0","isOutForward":"0","forwardType":"0","mobForwardType":2,"interactionNum":"","praiseTimes":"0","pic":"https://imgpai.thepaper.cn/newpai/image/1749980694857_bM2AwG_1749980695026.png","imgCardMode":0,"smallPic":"https://imgpai.thepaper.cn/newpai/image/1749980694857_bM2AwG_1749980695026.png?x-oss-process=image/resize,w_332","sharePic":"https://imgpai.thepaper.cn/newpai/image/1749980694871_Q7FJJS_1749980695086.png","pubTime":"41分钟前","pubTimeNew":"41分钟前","name":"台风“蝴蝶”致多地持续较强降雨，国家防总办公室等部署防汛防台风工作","closePraise":"0","nodeInfo":{"nodeId":25428,"name":"直击现场","desc":"第一现场，文图视频直播","pic":"https://imagecloud.thepaper.cn/thepaper/image/4/158/70.png","nodeType":0,"channelType":0,"forwordType":22,"forwardType":"22","liveType":"2","parentId":25388,"isOrder":"0","dataType":"0","shareName":"直击现场","nickName":"","mobForwardType":"22","summarize":"最快的现场新闻，最全的现场记录。我是你的眼睛，我就在现场。","color":"","videoLivingRoomDes":"","wwwSpecNodeAlign":0,"govAffairsType":"","showSpecialBanner":false,"showSpecialTopDesc":false,"topBarTypeCustomColor":false,"showVideoBottomRightBtn":false},"nodeId":25428,"contType":0,"pubTimeLong":1749981147564,"specialNodeId":0,"cardMode":"101","dataObjId":52,"closeFrontComment":false,"isSupInteraction":false,"tagList":[{"tagId":17471,"tag":"台风","isOrder":"0","isUpdateNotify":"0","isWonderfulComments":"0"},{"tagId":125092,"tag":"防汛","isOrder":"0","isUpdateNotify":"0","isWonderfulComments":"0"},{"tagId":343354,"tag":"防台风","isOrder":"0","isUpdateNotify":"0","isWonderfulComments":"0"}],"hideVideoFlag":false,"praiseStyle":1,"isSustainedFly":0,"softLocType":1,"closeComment":false,"voiceInfo":{"voiceSrc":"https://audios.thepaper.cn/input/30987713_202506151752a7d978ef-4757-4008-bd6b-36ff3c38dbd9.mp3","imgSrc":"https://imgpai.thepaper.cn/newpai/image/1749980694871_Q7FJJS_1749980695086.png","isHaveVoice":"1"},"softAdTypeStr":"1,1,1","originalContId":30987713,"paywalled":false,"audiovisualBlogSwitch":false,"audiovisualBlogGuests":""},{"contId":"30987365","isOutForword":"0","isOutForward":"0","forwardType":"0","mobForwardType":2,"interactionNum":"","praiseTimes":"49","pic":"https://imgpai.thepaper.cn/newpai/image/1749970707016_YwfzJt_1749970707202.png","imgCardMode":0,"smallPic":"https://imgpai.thepaper.cn/newpai/image/1749970707016_YwfzJt_1749970707202.png?x-oss-process=image/resize,w_332","sharePic":"https://imgpai.thepaper.cn/newpai/image/1749970707017_sFhSKr_1749970707305.png","pubTime":"49分钟前","pubTimeNew":"49分钟前","name":"签约平台倒闭多名游戏主播在其他平台直播被判违约，部分主播已上诉","closePraise":"0","nodeInfo":{"nodeId":25424,"name":"一号专案","desc":"司法个案，法治调查","pic":"https://imagecloud.thepaper.cn/thepaper/image/4/158/67.png","nodeType":0,"channelType":0,"forwordType":22,"forwardType":"22","liveType":"2","parentId":25388,"isOrder":"0","dataType":"0","shareName":"一号专案","nickName":"","mobForwardType":"22","summarize":"发掘大、要、新、奇司法个案，以独立专业调查、敏锐细致观察，创建新的政法新闻报道范式。","color":"","videoLivingRoomDes":"","wwwSpecNodeAlign":0,"govAffairsType":"","showSpecialBanner":false,"showSpecialTopDesc":false,"topBarTypeCustomColor":false,"showVideoBottomRightBtn":false},"nodeId":25424,"contType":0,"pubTimeLong":1749980682028,"specialNodeId":0,"cardMode":"101","dataObjId":52,"closeFrontComment":false,"isSupInteraction":false,"tagList":[{"tagId":98946,"tag":"主播","isOrder":"0","isUpdateNotify":"0","isWonderfulComments":"0"},{"tagId":45716,"tag":"直播","isOrder":"0","isUpdateNotify":"0","isWonderfulComments":"0"},{"tagId":50578,"tag":"未成年人","isOrder":"0","isUpdateNotify":"0","isWonderfulComments":"0"}],"hideVideoFlag":false,"praiseStyle":1,"isSustainedFly":0,"softLocType":1,"closeComment":false,"voiceInfo":{"voiceSrc":"https://audios.thepaper.cn/input/30987365_202506151744820292aa-1cf6-4e77-8645-303368ea705d.mp3","imgSrc":"https://imgpai.thepaper.cn/newpai/image/1749970707017_sFhSKr_1749970707305.png","isHaveVoice":"1"},"softAdTypeStr":"1,1,1","originalContId":30987365,"paywalled":false,"audiovisualBlogSwitch":false,"audiovisualBlogGuests":""},{"contId":"30987679","isOutForword":"0","isOutForward":"0","forwardType":"0","mobForwardType":2,"interactionNum":"12","praiseTimes":"27","pic":"https://imgpai.thepaper.cn/newpai/image/1749980089297_DEWXWz_1749980089510.png","imgCardMode":0,"smallPic":"https://imgpai.thepaper.cn/newpai/image/1749980089297_DEWXWz_1749980089510.png?x-oss-process=image/resize,w_332","sharePic":"https://imgpai.thepaper.cn/newpai/image/1749980089301_hS8Fwi_1749980089537.png","pubTime":"1小时前","pubTimeNew":"1小时前","name":"南部战区位南海组织海空联合巡航：任何搅局南海、制造热点的军事活动尽在掌握","closePraise":"0","nodeInfo":{"nodeId":25430,"name":"澎湃防务","desc":"传递最新鲜、专业的全球防务新闻，探析军事发展趋势","pic":"https://imagecloud.thepaper.cn/thepaper/image/4/158/77.png","nodeType":0,"channelType":0,"forwordType":22,"forwardType":"22","liveType":"2","parentId":25388,"isOrder":"0","dataType":"0","shareName":"澎湃防务","nickName":"","publishTime":1708421052562,"mobForwardType":"22","summarize":"通过新媒体多元的表达方式，向读者传递最新鲜、专业的全球防务新闻，探析军事发展趋势。","color":"","videoLivingRoomDes":"","wwwSpecNodeAlign":0,"govAffairsType":"","showSpecialBanner":false,"showSpecialTopDesc":false,"topBarTypeCustomColor":false,"showVideoBottomRightBtn":false},"nodeId":25430,"contType":0,"pubTimeLong":1749979079707,"specialNodeId":0,"cardMode":"101","dataObjId":52,"closeFrontComment":false,"isSupInteraction":false,"tagList":[{"tagId":263501,"tag":"南部战区","isOrder":"0","isUpdateNotify":"0","isWonderfulComments":"0"}],"hideVideoFlag":false,"praiseStyle":1,"isSustainedFly":0,"softLocType":1,"closeComment":false,"voiceInfo":{"voiceSrc":"https://audios.thepaper.cn/input/30987679_20250615174886358489-dee5-4245-81cf-1d009f2da4dc.mp3","imgSrc":"https://imgpai.thepaper.cn/newpai/image/1749980089301_hS8Fwi_1749980089537.png","isHaveVoice":"1"},"softAdTypeStr":"1,1,1","originalContId":30987679,"paywalled":false,"audiovisualBlogSwitch":false,"audiovisualBlogGuests":""},{"contId":"30987416","isOutForword":"0","isOutForward":"0","forwardType":"0","mobForwardType":2,"interactionNum":"","praiseTimes":"0","pic":"https://imgpai.thepaper.cn/newpai/image/1749973936187_HnzJfC_1749973936440.png","imgCardMode":0,"smallPic":"https://imgpai.thepaper.cn/newpai/image/1749973936187_HnzJfC_1749973936440.png?x-oss-process=image/resize,w_332","sharePic":"https://imgpai.thepaper.cn/newpai/image/1749973936262_rhePnm_1749973936453.png","pubTime":"1小时前","pubTimeNew":"1小时前","name":"印度政府就坠机事故召开新闻发布会，承诺3个月内公布调查报告","closePraise":"0","nodeInfo":{"nodeId":25429,"name":"全球速报","desc":"最热点的全球资讯","pic":"https://imagecloud.thepaper.cn/thepaper/image/4/158/73.png","nodeType":0,"channelType":0,"forwordType":22,"forwardType":"22","liveType":"2","parentId":25388,"isOrder":"0","dataType":"0","shareName":"全球速报","nickName":"","publishTime":1668726066292,"mobForwardType":"22","summarize":"最热点的全球资讯","color":"","videoLivingRoomDes":"","wwwSpecNodeAlign":0,"govAffairsType":"","showSpecialBanner":false,"showSpecialTopDesc":false,"topBarTypeCustomColor":false,"showVideoBottomRightBtn":false},"nodeId":25429,"contType":0,"pubTimeLong":1749978096339,"specialNodeId":0,"cardMode":"101","dataObjId":52,"closeFrontComment":false,"isSupInteraction":false,"tagList":[{"tagId":2144,"tag":"印度","isOrder":"0","isUpdateNotify":"0","isWonderfulComments":"0"},{"tagId":14064,"tag":"坠机","isOrder":"0","isUpdateNotify":"0","isWonderfulComments":"0"}],"hideVideoFlag":false,"praiseStyle":1,"isSustainedFly":0,"softLocType":1,"closeComment":false,"voiceInfo":{"voiceSrc":"https://audios.thepaper.cn/input/30987416_20250615170180e4028e-3528-4140-af61-05d6ed086b7b.mp3","imgSrc":"https://imgpai.thepaper.cn/newpai/image/1749973936262_rhePnm_1749973936453.png","isHaveVoice":"1"},"softAdTypeStr":"1,1,1","originalContId":30987416,"paywalled":false,"audiovisualBlogSwitch":false,"audiovisualBlogGuests":""},{"contId":"30987415","isOutForword":"0","isOutForward":"0","forwardType":"0","mobForwardType":2,"interactionNum":"15","praiseTimes":"3","pic":"https://imgpai.thepaper.cn/newpai/image/1749974349224_idjkx6_1749974349534.png","imgCardMode":0,"smallPic":"https://imgpai.thepaper.cn/newpai/image/1749974349224_idjkx6_1749974349534.png?x-oss-process=image/resize,w_332","sharePic":"https://imgpai.thepaper.cn/newpai/image/1749974349231_2M61X2_1749974349506.png","pubTime":"1小时前","pubTimeNew":"1小时前","name":"马上评｜《长安的荔枝》与职场理想主义的“退场”","closePraise":"0","nodeInfo":{"nodeId":27224,"name":"澎湃评论","desc":"在这里知道更多","pic":"https://imagecloud.thepaper.cn/thepaper/image/5/693/759.jpg","nodeType":0,"channelType":0,"forwordType":22,"forwardType":"22","liveType":"1","parentId":25389,"isOrder":"0","dataType":"0","shareName":"澎湃评论","nickName":"","mobForwardType":"22","summarize":"更多观点，更多解读。","color":"","videoLivingRoomDes":"","wwwSpecNodeAlign":0,"govAffairsType":"","showSpecialBanner":false,"showSpecialTopDesc":false,"topBarTypeCustomColor":false,"showVideoBottomRightBtn":false},"nodeId":27224,"contType":0,"pubTimeLong":1749977304301,"specialNodeId":0,"cardMode":"101","dataObjId":52,"closeFrontComment":false,"isSupInteraction":false,"tagList":[{"tagId":6449864,"tag":"长安的荔枝","isOrder":"0","isUpdateNotify":"0","isWonderfulComments":"0"}],"hideVideoFlag":false,"praiseStyle":1,"isSustainedFly":0,"softLocType":1,"closeComment":false,"voiceInfo":{"voiceSrc":"https://audios.thepaper.cn/input/30987415_2025061516480e5d5197-d79d-4abb-aa64-a71e77f6ffe3.mp3","imgSrc":"https://imgpai.thepaper.cn/newpai/image/1749974349231_2M61X2_1749974349506.png","isHaveVoice":"1"},"softAdTypeStr":"1,1,1","originalContId":30987415,"paywalled":false,"audiovisualBlogSwitch":false,"audiovisualBlogGuests":""},{"contId":"30987413","isOutForword":"0","isOutForward":"0","forwardType":"0","mobForwardType":2,"interactionNum":"","praiseTimes":"1","pic":"https://imgpai.thepaper.cn/newpai/image/1749974616845_NKbbNj_1749974617107.png","imgCardMode":0,"smallPic":"https://imgpai.thepaper.cn/newpai/image/1749974616845_NKbbNj_1749974617107.png?x-oss-process=image/resize,w_332","sharePic":"https://imgpai.thepaper.cn/newpai/image/1749974616847_GW7rTD_1749974617085.png","pubTime":"2小时前","pubTimeNew":"2小时前","name":"北航今年本科招生专业新增量子科技先锋计划及多个试验班","closePraise":"0","nodeInfo":{"nodeId":25487,"name":"教育家","desc":"最先进的教育理念在此碰撞","pic":"https://imagecloud.thepaper.cn/thepaper/image/4/158/83.png","nodeType":0,"channelType":0,"forwordType":22,"forwardType":"22","liveType":"2","parentId":25388,"isOrder":"0","dataType":"0","shareName":"教育家","nickName":"","mobForwardType":"22","summarize":"聚焦教育发展，剖析改革难题，将最前沿的教育理念与所有人分享。每个人都是教育家，只等你拿出真知灼见。","color":"","videoLivingRoomDes":"","wwwSpecNodeAlign":0,"govAffairsType":"","showSpecialBanner":false,"showSpecialTopDesc":false,"topBarTypeCustomColor":false,"showVideoBottomRightBtn":false},"nodeId":25487,"contType":0,"pubTimeLong":1749976283630,"specialNodeId":0,"cardMode":"101","dataObjId":52,"closeFrontComment":false,"isSupInteraction":false,"tagList":[{"tagId":117667,"tag":"北京航空航天大学","isOrder":"0","isUpdateNotify":"0","isWonderfulComments":"0"},{"tagId":4052,"tag":"招生","isOrder":"0","isUpdateNotify":"0","isWonderfulComments":"0"}],"hideVideoFlag":false,"praiseStyle":1,"isSustainedFly":0,"softLocType":1,"closeComment":false,"voiceInfo":{"voiceSrc":"https://audios.thepaper.cn/input/30987413_20250615163127ddc924-552e-4ccf-a2a1-6ea6d9e81fee.mp3","imgSrc":"https://imgpai.thepaper.cn/newpai/image/1749974616847_GW7rTD_1749974617085.png","isHaveVoice":"1"},"softAdTypeStr":"1,1,1","originalContId":30987413,"paywalled":false,"audiovisualBlogSwitch":false,"audiovisualBlogGuests":""},{"contId":"30987427","isOutForword":"0","isOutForward":"0","forwardType":"0","mobForwardType":2,"interactionNum":"28","praiseTimes":"11","pic":"https://imgpai.thepaper.cn/newpai/image/1749974435702_TGzzCG_1749974436021.png","imgCardMode":0,"smallPic":"https://imgpai.thepaper.cn/newpai/image/1749974435702_TGzzCG_1749974436021.png?x-oss-process=image/resize,w_332","sharePic":"https://imgpai.thepaper.cn/newpai/image/1749974435762_2icwAb_1749974435972.png","pubTime":"2小时前","pubTimeNew":"2小时前","name":"重仓泡泡玛特的95后基金经理：买Labubu到底是在买啥？","closePraise":"0","nodeInfo":{"nodeId":25437,"name":"牛市点线面","desc":"简单专业时尚的财富平台","pic":"https://imagecloud.thepaper.cn/thepaper/image/4/158/90.png","nodeType":0,"channelType":0,"forwordType":22,"forwardType":"22","liveType":"2","parentId":25388,"isOrder":"0","dataType":"0","shareName":"牛市点线面","nickName":"","mobForwardType":"22","summarize":"对话顶级资本大佬和有点闲钱的人士，提供独家财富资讯和理财思考，为投资人和财富管理者搭建有趣的沟通平台，一起拆解资金本色和资产成色。","color":"","videoLivingRoomDes":"","wwwSpecNodeAlign":0,"govAffairsType":"","showSpecialBanner":false,"showSpecialTopDesc":false,"topBarTypeCustomColor":false,"showVideoBottomRightBtn":false},"nodeId":25437,"contType":0,"pubTimeLong":1749974451495,"specialNodeId":0,"cardMode":"101","dataObjId":52,"closeFrontComment":false,"isSupInteraction":false,"tagList":[{"tagId":6196289,"tag":"Labubu","isOrder":"0","isUpdateNotify":"0","isWonderfulComments":"0"}],"hideVideoFlag":false,"praiseStyle":1,"isSustainedFly":0,"softLocType":1,"closeComment":false,"voiceInfo":{"voiceSrc":"https://audios.thepaper.cn/input/30987427_202506151601b9e2c225-eb86-40c7-82d7-f9e7ab8627dc.mp3","imgSrc":"https://imgpai.thepaper.cn/newpai/image/1749974435762_2icwAb_1749974435972.png","isHaveVoice":"1"},"softAdTypeStr":"1,1,1","originalContId":30987427,"paywalled":false,"audiovisualBlogSwitch":false,"audiovisualBlogGuests":""},{"contId":"30987407","isOutForword":"0","isOutForward":"0","forwardType":"0","mobForwardType":2,"interactionNum":"","praiseTimes":"4","pic":"https://imgpai.thepaper.cn/newpai/image/1749972001858_nReP3p_1749972002078.png","imgCardMode":0,"smallPic":"https://imgpai.thepaper.cn/newpai/image/1749972001858_nReP3p_1749972002078.png?x-oss-process=image/resize,w_332","sharePic":"https://imgpai.thepaper.cn/newpai/image/1749972001896_cJ6t2m_1749972002367.png","pubTime":"3小时前","pubTimeNew":"3小时前","name":"以色列说伊朗导弹袭击致6死180伤","closePraise":"0","nodeInfo":{"nodeId":25429,"name":"全球速报","desc":"最热点的全球资讯","pic":"https://imagecloud.thepaper.cn/thepaper/image/4/158/73.png","nodeType":0,"channelType":0,"forwordType":22,"forwardType":"22","liveType":"2","parentId":25388,"isOrder":"0","dataType":"0","shareName":"全球速报","nickName":"","publishTime":1668726066292,"mobForwardType":"22","summarize":"最热点的全球资讯","color":"","videoLivingRoomDes":"","wwwSpecNodeAlign":0,"govAffairsType":"","showSpecialBanner":false,"showSpecialTopDesc":false,"topBarTypeCustomColor":false,"showVideoBottomRightBtn":false},"nodeId":25429,"contType":0,"pubTimeLong":1749972725244,"specialNodeId":0,"cardMode":"101","dataObjId":52,"closeFrontComment":false,"isSupInteraction":false,"tagList":[{"tagId":6109136,"tag":"伊以冲突","isOrder":"0","isUpdateNotify":"0","isWonderfulComments":"0"}],"hideVideoFlag":false,"praiseStyle":1,"isSustainedFly":0,"softLocType":1,"closeComment":false,"voiceInfo":{"voiceSrc":"https://audios.thepaper.cn/input/30987407_202506151532db949249-edc1-464f-b80a-cbc93952856e.mp3","imgSrc":"https://imgpai.thepaper.cn/newpai/image/1749972001896_cJ6t2m_1749972002367.png","isHaveVoice":"1"},"softAdTypeStr":"1,1,1","originalContId":30987407,"paywalled":false,"audiovisualBlogSwitch":false,"audiovisualBlogGuests":""},{"contId":"30987362","isOutForword":"0","isOutForward":"0","forwardType":"0","mobForwardType":2,"interactionNum":"47","praiseTimes":"103","pic":"https://imgpai.thepaper.cn/newpai/image/1749970635955_txf315_1749970636176.png","imgCardMode":0,"smallPic":"https://imgpai.thepaper.cn/newpai/image/1749970635955_txf315_1749970636176.png?x-oss-process=image/resize,w_332","sharePic":"https://imgpai.thepaper.cn/newpai/image/1749970636001_8G2HE1_1749970636308.png","pubTime":"3小时前","pubTimeNew":"3小时前","name":"中传公布优秀毕业生去向：建党百年庆典领诵团成员沈倩拟入职新华社","closePraise":"0","nodeInfo":{"nodeId":25487,"name":"教育家","desc":"最先进的教育理念在此碰撞","pic":"https://imagecloud.thepaper.cn/thepaper/image/4/158/83.png","nodeType":0,"channelType":0,"forwordType":22,"forwardType":"22","liveType":"2","parentId":25388,"isOrder":"0","dataType":"0","shareName":"教育家","nickName":"","mobForwardType":"22","summarize":"聚焦教育发展，剖析改革难题，将最前沿的教育理念与所有人分享。每个人都是教育家，只等你拿出真知灼见。","color":"","videoLivingRoomDes":"","wwwSpecNodeAlign":0,"govAffairsType":"","showSpecialBanner":false,"showSpecialTopDesc":false,"topBarTypeCustomColor":false,"showVideoBottomRightBtn":false},"nodeId":25487,"contType":0,"pubTimeLong":1749972071036,"specialNodeId":0,"cardMode":"101","dataObjId":52,"closeFrontComment":false,"isSupInteraction":false,"tagList":[{"tagId":380505,"tag":"中传","isOrder":"0","isUpdateNotify":"0","isWonderfulComments":"0"}],"hideVideoFlag":false,"praiseStyle":1,"isSustainedFly":0,"softLocType":1,"closeComment":false,"voiceInfo":{"voiceSrc":"https://audios.thepaper.cn/input/30987362_20250615152124b6a1cc-a0c0-446e-8247-e2f537cf6cd1.mp3","imgSrc":"https://imgpai.thepaper.cn/newpai/image/1749970636001_8G2HE1_1749970636308.png","isHaveVoice":"1"},"softAdTypeStr":"1,1,1","originalContId":30987362,"paywalled":false,"audiovisualBlogSwitch":false,"audiovisualBlogGuests":""},{"contId":"30987405","isOutForword":"0","isOutForward":"0","forwardType":"0","mobForwardType":2,"interactionNum":"62","praiseTimes":"9","pic":"https://imgpai.thepaper.cn/newpai/image/1749971804641_5rFtzf_1749971804951.png","imgCardMode":0,"smallPic":"https://imgpai.thepaper.cn/newpai/image/1749971804641_5rFtzf_1749971804951.png?x-oss-process=image/resize,w_332","sharePic":"https://imgpai.thepaper.cn/newpai/image/1749971804691_n33EZt_1749971804908.png","pubTime":"3小时前","pubTimeNew":"3小时前","name":"以军向伊朗核反应堆和武器工厂周围人员发布撤离警告","closePraise":"0","nodeInfo":{"nodeId":25429,"name":"全球速报","desc":"最热点的全球资讯","pic":"https://imagecloud.thepaper.cn/thepaper/image/4/158/73.png","nodeType":0,"channelType":0,"forwordType":22,"forwardType":"22","liveType":"2","parentId":25388,"isOrder":"0","dataType":"0","shareName":"全球速报","nickName":"","publishTime":1668726066292,"mobForwardType":"22","summarize":"最热点的全球资讯","color":"","videoLivingRoomDes":"","wwwSpecNodeAlign":0,"govAffairsType":"","showSpecialBanner":false,"showSpecialTopDesc":false,"topBarTypeCustomColor":false,"showVideoBottomRightBtn":false},"nodeId":25429,"contType":0,"pubTimeLong":1749971951196,"specialNodeId":0,"cardMode":"101","dataObjId":52,"closeFrontComment":false,"isSupInteraction":false,"tagList":[{"tagId":6109136,"tag":"伊以冲突","isOrder":"0","isUpdateNotify":"0","isWonderfulComments":"0"}],"hideVideoFlag":false,"praiseStyle":1,"isSustainedFly":0,"softLocType":1,"closeComment":false,"voiceInfo":{"voiceSrc":"https://audios.thepaper.cn/input/30987405_2025061515193ec06668-9786-4136-bfba-003fedb5bf6e.mp3","imgSrc":"https://imgpai.thepaper.cn/newpai/image/1749971804691_n33EZt_1749971804908.png","isHaveVoice":"1"},"softAdTypeStr":"1,1,1","originalContId":30987405,"paywalled":false,"audiovisualBlogSwitch":false,"audiovisualBlogGuests":""}],"expressNewsOpenFlag":false}}