{"resultCode":1,"resultMsg":"操作成功","systemTime":1732746621840,"data":{"interleavePropagandaList":[[{"id":31,"imgSrc":"https://imagecloud.thepaper.cn/recommend/xuanchuanwei/20241025182414078_2_2_d823584f-6d27-4470-905e-fe699b80a73d.png","imgWidth":720,"imgHeight":270,"link":"https://open.thepaper.cn","type":1}],[{"id":20,"imgSrc":"https://imagecloud.thepaper.cn/recommend/xuanchuanwei/20240904172338577_3_2_bbbfced3-9ab2-45ba-b20f-975333c0f4f8.jpg","imgWidth":720,"imgHeight":270,"link":"https://tousu.thepaper.cn/www/","type":1},{"id":41,"imgSrc":"https://imagecloud.thepaper.cn/recommend/xuanchuanwei/20240511110623297_3_3_1d6a132d-5d23-45b8-b5b7-b637924698d3.jpg","imgWidth":480,"imgHeight":180,"link":"https://www.thepaper.cn/newsDetail_forward_27325323","type":1}],[{"id":27,"imgSrc":"https://imagecloud.thepaper.cn/recommend/xuanchuanwei/20220812145322429_4_7_80d7d312-d32e-4e3b-b6ac-a1d0e917b207.jpg","imgWidth":200,"imgHeight":75,"link":"","type":1},{"id":28,"imgSrc":"https://imagecloud.thepaper.cn/recommend/xuanchuanwei/20220812145322502_4_8_c70c98db-41e9-46da-b700-9db3fc6c50b2.png","imgWidth":600,"imgHeight":225,"link":"","type":1},{"id":29,"imgSrc":"https://imagecloud.thepaper.cn/recommend/xuanchuanwei/20220812145322525_4_9_88c7dd2b-3091-423e-8319-5890aa745e8f.jpg","imgWidth":200,"imgHeight":75,"link":"https://newsxmwb.xinmin.cn/special/mljbzsjs/index.html","type":1},{"id":22,"imgSrc":"https://imagecloud.thepaper.cn/recommend/xuanchuanwei/20220809142338266_4_2_ef4aba58-ed61-4a3d-963d-b572e06202d8.jpg","imgWidth":200,"imgHeight":75,"link":"https://www.12377.cn","type":1},{"id":37,"imgSrc":"https://imagecloud.thepaper.cn/recommend/xuanchuanwei/20230628161703112_4_10_8437f3f3-89ae-4cc6-90fe-a9ab27640140.jpg","imgWidth":400,"imgHeight":180,"link":"https://www.thepaper.cn/newsDetail_forward_128593","type":1},{"id":23,"imgSrc":"https://imagecloud.thepaper.cn/recommend/xuanchuanwei/20220809142338298_4_3_990e577f-c051-4b7a-84fe-6247eb4913a0.jpg","imgWidth":200,"imgHeight":75,"link":"http://www.shjbzx.cn","type":1},{"id":25,"imgSrc":"https://imagecloud.thepaper.cn/recommend/xuanchuanwei/20220809142338440_4_5_deb0b110-a35d-46d5-9065-953ac61d5cdc.jpg","imgWidth":200,"imgHeight":75,"link":"https://www.12377.cn","type":1},{"id":26,"imgSrc":"https://imagecloud.thepaper.cn/recommend/xuanchuanwei/20220809142338492_4_6_6378a6e4-6574-4da7-9d10-803bbdb33e66.jpg","imgWidth":200,"imgHeight":75,"link":"http://www.cyberpolice.cn/wfjb/ ","type":1}]],"morningEveningNews":[{"name":"去台湾","nodeId":148397,"contType":0,"cardMode":"101","praiseStyle":0,"isSustainedFly":0,"softLocType":0},{"contId":"29472265","isOutForword":"0","isOutForward":"0","forwardType":"0","mobForwardType":2,"imgCardMode":0,"smallPic":"https://imagecloud.thepaper.cn/thepaper/image/331/369/477.jpg?x-oss-process=image/resize,w_332","sharePic":"https://imagecloud.thepaper.cn/thepaper/image/331/369/478.jpg","pubTime":"15小时前","pubTimeNew":"15小时前","summary":"外交部发言人毛宁：中方认为，加沙未能实现停火止战是中东局势本轮动荡的根源，各方应当携手推动加沙早日全面持久停火。","name":"外交部回应黎以达成停火协议","closePraise":"0","nodeInfo":{"nodeId":122905,"name":"大国外交","desc":"构建人类命运共同体","pic":"https://imagecloud.thepaper.cn/thepaper/image/225/728/225.png","nodeType":0,"channelType":0,"forwordType":22,"forwardType":"22","liveType":"2","parentId":25388,"isOrder":"0","dataType":"0","shareName":"大国外交","nickName":"","publishTime":1668726187654,"mobForwardType":"22","summarize":"构建人类命运共同体","color":"","videoLivingRoomDes":"","wwwSpecNodeAlign":0,"govAffairsType":"","showSpecialBanner":false,"showSpecialTopDesc":false,"topBarTypeCustomColor":false,"showVideoBottomRightBtn":false},"nodeId":122905,"contType":0,"pubTimeLong":1732692166233,"specialNodeId":0,"cardMode":"101","dataObjId":52,"closeFrontComment":false,"isSupInteraction":false,"tagList":[{"tagId":36426,"tag":"外交部例行记者会","isOrder":"0","isUpdateNotify":"0","isWonderfulComments":"0"}],"hideVideoFlag":false,"praiseStyle":1,"isSustainedFly":0,"softLocType":1,"closeComment":false,"softAdTypeStr":"1,1,1"},{"contId":"29472134","isOutForword":"0","isOutForward":"0","forwardType":"0","mobForwardType":2,"imgCardMode":0,"smallPic":"https://imagecloud.thepaper.cn/thepaper/image/331/367/980.png?x-oss-process=image/resize,w_332","sharePic":"https://imagecloud.thepaper.cn/thepaper/image/331/367/981.png","pubTime":"16小时前","pubTimeNew":"16小时前","summary":"经调查认定，这是一起违规改装的电动自行车超标大容量锂离子电池热失控起火引起的重大火灾责任事故。10人因涉嫌犯罪，被公安机关依法采取刑事强制措施。","name":"南京“2·23”火灾调查报告公布","closePraise":"0","nodeInfo":{"nodeId":25491,"name":"长三角政商","desc":"解读区域政情与财富故事","pic":"https://imagecloud.thepaper.cn/thepaper/image/4/158/69.png","nodeType":0,"channelType":0,"forwordType":22,"forwardType":"22","liveType":"2","parentId":25388,"isOrder":"0","dataType":"0","shareName":"长三角政商","nickName":"","mobForwardType":"22","summarize":"深耕中国最大都市群，阐释、发微、钩沉“富贵门”里形形色色的政情动向与财富故事，以及这块冲积平原对中国政经情势放射的冲击波。","color":"","videoLivingRoomDes":"","wwwSpecNodeAlign":0,"govAffairsType":"","showSpecialBanner":false,"showSpecialTopDesc":false,"topBarTypeCustomColor":false,"showVideoBottomRightBtn":false},"nodeId":25491,"contType":0,"pubTimeLong":1732687692233,"specialNodeId":0,"cardMode":"101","dataObjId":52,"closeFrontComment":false,"isSupInteraction":false,"tagList":[{"tagId":344672,"tag":"火灾事故","isOrder":"0","isUpdateNotify":"0","isWonderfulComments":"0"}],"hideVideoFlag":false,"praiseStyle":1,"isSustainedFly":0,"softLocType":1,"closeComment":false,"softAdTypeStr":"1,1,1"}],"financialInformationNews":[{"contId":"29476784","isOutForword":"0","isOutForward":"0","forwardType":"67","mobForwardType":67,"pic":"https://imagecloud.thepaper.cn/thepaper/image/331/421/784.png","imgCardMode":0,"smallPic":"https://imagecloud.thepaper.cn/thepaper/image/331/421/784.png?x-oss-process=image/resize,w_332","sharePic":"https://imagecloud.thepaper.cn/thepaper/image/331/421/782.jpg","pubTime":"7小时前","pubTimeNew":"7小时前","name":"美股三大指数开盘涨跌不一，热门中概股普涨","closePraise":"0","nodeInfo":{"name":"澎湃财讯","desc":"","nodeType":0,"channelType":0,"forwardType":"22","liveType":"1","parentId":0,"isOrder":"0","dataType":"0","shareName":"澎湃财讯","nickName":"","publishTime":1618889006598,"mobForwardType":"22","summarize":"","color":"","videoLivingRoomDes":"","wwwSpecNodeAlign":0,"govAffairsType":"","showSpecialBanner":false,"showSpecialTopDesc":false,"topBarTypeCustomColor":false,"showVideoBottomRightBtn":false},"nodeId":105435,"contType":13,"pubTimeLong":1732718518456,"specialNodeId":0,"cardMode":"101","dataObjId":52,"closeFrontComment":false,"isSupInteraction":false,"hideVideoFlag":false,"praiseStyle":0,"isSustainedFly":0,"softLocType":1,"closeComment":false,"voiceInfo":{"imgSrc":"https://imagecloud.thepaper.cn/thepaper/image/331/421/782.jpg","isHaveVoice":"1"},"softAdTypeStr":"1"},{"contId":"29475818","isOutForword":"0","isOutForward":"0","forwardType":"67","mobForwardType":67,"pic":"https://imagecloud.thepaper.cn/thepaper/image/331/408/744.png","imgCardMode":0,"smallPic":"https://imagecloud.thepaper.cn/thepaper/image/331/408/744.png?x-oss-process=image/resize,w_332","sharePic":"https://imagecloud.thepaper.cn/thepaper/image/331/408/742.jpg","pubTime":"9小时前","pubTimeNew":"9小时前","name":"国内期货夜盘开盘涨跌不一，沪金涨0.69%","closePraise":"0","nodeInfo":{"name":"澎湃财讯","desc":"","nodeType":0,"channelType":0,"forwardType":"22","liveType":"1","parentId":0,"isOrder":"0","dataType":"0","shareName":"澎湃财讯","nickName":"","publishTime":1618889006598,"mobForwardType":"22","summarize":"","color":"","videoLivingRoomDes":"","wwwSpecNodeAlign":0,"govAffairsType":"","showSpecialBanner":false,"showSpecialTopDesc":false,"topBarTypeCustomColor":false,"showVideoBottomRightBtn":false},"nodeId":105435,"contType":13,"pubTimeLong":1732712824686,"specialNodeId":0,"cardMode":"101","dataObjId":52,"closeFrontComment":false,"isSupInteraction":false,"hideVideoFlag":false,"praiseStyle":0,"isSustainedFly":0,"softLocType":1,"closeComment":false,"voiceInfo":{"imgSrc":"https://imagecloud.thepaper.cn/thepaper/image/331/408/742.jpg","isHaveVoice":"1"},"softAdTypeStr":"1"}],"hotNews":[{"contId":"29470692","isOutForword":"0","isOutForward":"0","forwardType":"0","mobForwardType":2,"interactionNum":"84","praiseTimes":"529","pic":"https://imagecloud.thepaper.cn/thepaper/image/331/352/595.png","imgCardMode":0,"smallPic":"https://imagecloud.thepaper.cn/thepaper/image/331/352/595.png?x-oss-process=image/resize,w_332","sharePic":"https://imagecloud.thepaper.cn/thepaper/image/331/352/596.png","pubTime":"20小时前","pubTimeNew":"20小时前","name":"上海市委常委、浦东新区区委书记朱芝松接受审查调查","closePraise":"0","nodeInfo":{"nodeId":25422,"name":"浦江头条","desc":"上海每天最重要的事件","pic":"https://imagecloud.thepaper.cn/thepaper/image/4/158/81.png","nodeType":0,"channelType":0,"forwordType":22,"forwardType":"22","liveType":"1","parentId":25388,"isOrder":"0","dataType":"0","shareName":"浦江头条","nickName":"","mobForwardType":"22","recommendIds":[13851102],"summarize":"不满足于最动态，还要最重要；丰富而不琐碎，快速但不轻浮。你最想关注的上海新闻，这里肯定有，你应该知道的上海新闻，这里也会有。","color":"","videoLivingRoomDes":"","wwwSpecNodeAlign":0,"govAffairsType":"","showSpecialBanner":false,"showSpecialTopDesc":false,"topBarTypeCustomColor":false,"showVideoBottomRightBtn":false},"nodeId":25422,"contType":0,"pubTimeLong":1732673043649,"specialNodeId":0,"cardMode":"101","dataObjId":52,"closeFrontComment":false,"isSupInteraction":false,"tagList":[{"tagId":2868967,"tag":"朱芝松","isOrder":"0","isUpdateNotify":"0","isWonderfulComments":"0"}],"hideVideoFlag":false,"praiseStyle":1,"isSustainedFly":0,"softLocType":1,"closeComment":false,"voiceInfo":{"imgSrc":"https://imagecloud.thepaper.cn/thepaper/image/331/352/596.png","isHaveVoice":"1"},"softAdTypeStr":"1,1,1"},{"contId":"29471046","isOutForword":"0","isOutForward":"0","forwardType":"0","mobForwardType":2,"interactionNum":"103","praiseTimes":"89","pic":"https://imagecloud.thepaper.cn/thepaper/image/331/355/469.jpg","imgCardMode":0,"smallPic":"https://imagecloud.thepaper.cn/thepaper/image/331/355/469.jpg?x-oss-process=image/resize,w_332","sharePic":"https://imagecloud.thepaper.cn/thepaper/image/331/355/472.jpg","pubTime":"18小时前","pubTimeNew":"18小时前","name":"比亚迪回应要求供应商降价10%：年度议价是行业惯例，提降价目标非强制要求","closePraise":"0","nodeInfo":{"nodeId":25434,"name":"10%公司","desc":"派发上市公司变革红利","pic":"https://imagecloud.thepaper.cn/thepaper/image/4/158/87.png","nodeType":0,"channelType":0,"forwordType":22,"forwardType":"22","liveType":"1","parentId":25388,"isOrder":"0","dataType":"0","shareName":"10%公司","nickName":"","mobForwardType":"22","summarize":"聚焦公司变革，致力于发现10%最优质公司。","color":"","videoLivingRoomDes":"","wwwSpecNodeAlign":0,"govAffairsType":"","showSpecialBanner":false,"showSpecialTopDesc":false,"topBarTypeCustomColor":false,"showVideoBottomRightBtn":false},"nodeId":25434,"contType":0,"pubTimeLong":1732679815117,"specialNodeId":0,"cardMode":"101","dataObjId":52,"closeFrontComment":false,"isSupInteraction":false,"tagList":[{"tagId":22983,"tag":"比亚迪","isOrder":"0","isUpdateNotify":"0","isWonderfulComments":"0"}],"hideVideoFlag":false,"praiseStyle":1,"isSustainedFly":0,"softLocType":1,"closeComment":false,"voiceInfo":{"imgSrc":"https://imagecloud.thepaper.cn/thepaper/image/331/355/472.jpg","isHaveVoice":"1"},"softAdTypeStr":"1,1,1"},{"contId":"29469700","isOutForword":"0","isOutForward":"0","forwardType":"0","mobForwardType":2,"interactionNum":"56","praiseTimes":"144","pic":"https://imagecloud.thepaper.cn/thepaper/image/331/339/671.png","imgCardMode":0,"smallPic":"https://imagecloud.thepaper.cn/thepaper/image/331/339/671.png?x-oss-process=image/resize,w_332","sharePic":"https://imagecloud.thepaper.cn/thepaper/image/331/339/672.png","pubTime":"22小时前","pubTimeNew":"22小时前","name":"黎以停火协议即将生效：以军仍在狂轰滥炸，停火真能落实吗？","closePraise":"0","nodeInfo":{"nodeId":25429,"name":"全球速报","desc":"最热点的全球资讯","pic":"https://imagecloud.thepaper.cn/thepaper/image/4/158/73.png","nodeType":0,"channelType":0,"forwordType":22,"forwardType":"22","liveType":"2","parentId":25388,"isOrder":"0","dataType":"0","shareName":"全球速报","nickName":"","publishTime":1668726066292,"mobForwardType":"22","summarize":"最热点的全球资讯","color":"","videoLivingRoomDes":"","wwwSpecNodeAlign":0,"govAffairsType":"","showSpecialBanner":false,"showSpecialTopDesc":false,"topBarTypeCustomColor":false,"showVideoBottomRightBtn":false},"nodeId":25429,"contType":0,"pubTimeLong":1732665605044,"specialNodeId":0,"cardMode":"101","dataObjId":52,"closeFrontComment":false,"isSupInteraction":false,"tagList":[{"tagId":6440270,"tag":"黎以","isOrder":"0","isUpdateNotify":"0","isWonderfulComments":"0"},{"tagId":4646,"tag":"以色列","isOrder":"0","isUpdateNotify":"0","isWonderfulComments":"0"}],"hideVideoFlag":false,"praiseStyle":1,"isSustainedFly":0,"softLocType":1,"closeComment":false,"voiceInfo":{"imgSrc":"https://imagecloud.thepaper.cn/thepaper/image/331/339/672.png","isHaveVoice":"1"},"softAdTypeStr":"1,1,1"},{"contId":"29472134","isOutForword":"0","isOutForward":"0","forwardType":"0","mobForwardType":2,"interactionNum":"78","praiseTimes":"375","pic":"https://imagecloud.thepaper.cn/thepaper/image/331/367/980.png","imgCardMode":0,"smallPic":"https://imagecloud.thepaper.cn/thepaper/image/331/367/980.png?x-oss-process=image/resize,w_332","sharePic":"https://imagecloud.thepaper.cn/thepaper/image/331/367/981.png","pubTime":"16小时前","pubTimeNew":"16小时前","name":"南京“2·23”15死44伤火灾事故调查报告公布，10人被处罚","closePraise":"0","nodeInfo":{"nodeId":25491,"name":"长三角政商","desc":"解读区域政情与财富故事","pic":"https://imagecloud.thepaper.cn/thepaper/image/4/158/69.png","nodeType":0,"channelType":0,"forwordType":22,"forwardType":"22","liveType":"2","parentId":25388,"isOrder":"0","dataType":"0","shareName":"长三角政商","nickName":"","mobForwardType":"22","summarize":"深耕中国最大都市群，阐释、发微、钩沉“富贵门”里形形色色的政情动向与财富故事，以及这块冲积平原对中国政经情势放射的冲击波。","color":"","videoLivingRoomDes":"","wwwSpecNodeAlign":0,"govAffairsType":"","showSpecialBanner":false,"showSpecialTopDesc":false,"topBarTypeCustomColor":false,"showVideoBottomRightBtn":false},"nodeId":25491,"contType":0,"pubTimeLong":1732687692233,"specialNodeId":0,"cardMode":"101","dataObjId":52,"closeFrontComment":false,"isSupInteraction":false,"tagList":[{"tagId":344672,"tag":"火灾事故","isOrder":"0","isUpdateNotify":"0","isWonderfulComments":"0"}],"hideVideoFlag":false,"praiseStyle":1,"isSustainedFly":0,"softLocType":1,"closeComment":false,"voiceInfo":{"imgSrc":"https://imagecloud.thepaper.cn/thepaper/image/331/367/981.png","isHaveVoice":"1"},"softAdTypeStr":"1,1,1"},{"contId":"29465197","isOutForword":"0","isOutForward":"0","forwardType":"0","mobForwardType":2,"interactionNum":"153","praiseTimes":"40","pic":"https://imagecloud.thepaper.cn/thepaper/image/331/285/977.jpg","imgCardMode":0,"smallPic":"https://imagecloud.thepaper.cn/thepaper/image/331/285/977.jpg?x-oss-process=image/resize,w_332","sharePic":"https://imagecloud.thepaper.cn/thepaper/image/331/285/978.jpg","pubTime":"23小时前","pubTimeNew":"23小时前","name":"中国恒大及许家印被广州南沙法院采取限制消费措施","closePraise":"0","nodeInfo":{"nodeId":25433,"name":"地产界","desc":"地产界所有你想知道的事儿","pic":"https://imagecloud.thepaper.cn/thepaper/image/4/158/86.png","nodeType":0,"channelType":0,"forwordType":22,"forwardType":"22","liveType":"1","parentId":25388,"isOrder":"0","dataType":"0","shareName":"地产界","nickName":"","mobForwardType":"22","summarize":"提供地产界最新的投资趋势、最热的地区规划、最深入的政策解读。","color":"","videoLivingRoomDes":"","wwwSpecNodeAlign":0,"govAffairsType":"","showSpecialBanner":false,"showSpecialTopDesc":false,"topBarTypeCustomColor":false,"showVideoBottomRightBtn":false},"nodeId":25433,"contType":0,"pubTimeLong":1732661970870,"specialNodeId":0,"cardMode":"101","dataObjId":52,"closeFrontComment":false,"isSupInteraction":false,"tagList":[{"tagId":630310,"tag":"中国恒大","isOrder":"0","isUpdateNotify":"0","isWonderfulComments":"0"}],"hideVideoFlag":false,"praiseStyle":1,"isSustainedFly":0,"softLocType":1,"closeComment":false,"voiceInfo":{"imgSrc":"https://imagecloud.thepaper.cn/thepaper/image/331/285/978.jpg","isHaveVoice":"1"},"softAdTypeStr":"1,1,1"},{"contId":"29471718","isOutForword":"0","isOutForward":"0","forwardType":"0","mobForwardType":2,"interactionNum":"125","praiseTimes":"77","pic":"https://imagecloud.thepaper.cn/thepaper/image/331/364/390.jpg","imgCardMode":0,"smallPic":"https://imagecloud.thepaper.cn/thepaper/image/331/364/390.jpg?x-oss-process=image/resize,w_332","sharePic":"https://imagecloud.thepaper.cn/thepaper/image/331/364/391.jpg","pubTime":"17小时前","pubTimeNew":"17小时前","name":"利好！七部门发文推进医疗机构检查检验结果互认","closePraise":"0","nodeInfo":{"nodeId":25425,"name":"绿政公署","desc":"环境与公共健康调查","pic":"https://imagecloud.thepaper.cn/thepaper/image/4/158/72.png","nodeType":0,"channelType":0,"forwordType":22,"forwardType":"22","liveType":"2","parentId":25388,"isOrder":"0","dataType":"0","shareName":"绿政公署","nickName":"","mobForwardType":"22","summarize":"专注环境领域调查，曝光公共健康隐患。公众都有免于恐惧的自由，万物都有健康生长的权利。","color":"","videoLivingRoomDes":"","wwwSpecNodeAlign":0,"govAffairsType":"","showSpecialBanner":false,"showSpecialTopDesc":false,"topBarTypeCustomColor":false,"showVideoBottomRightBtn":false},"nodeId":25425,"contType":0,"pubTimeLong":1732684972104,"specialNodeId":0,"cardMode":"101","dataObjId":52,"closeFrontComment":false,"isSupInteraction":false,"tagList":[{"tagId":6520619,"tag":"医疗机构检查检验结果互认","isOrder":"0","isUpdateNotify":"0","isWonderfulComments":"0"}],"hideVideoFlag":false,"praiseStyle":1,"isSustainedFly":0,"softLocType":1,"closeComment":false,"voiceInfo":{"imgSrc":"https://imagecloud.thepaper.cn/thepaper/image/331/364/391.jpg","isHaveVoice":"1"},"softAdTypeStr":"1,1,1"},{"contId":"29458923","isOutForword":"0","isOutForward":"0","forwardType":"0","mobForwardType":2,"interactionNum":"47","praiseTimes":"122","pic":"https://imagecloud.thepaper.cn/thepaper/image/331/248/731.jpg","imgCardMode":0,"smallPic":"https://imagecloud.thepaper.cn/thepaper/image/331/248/731.jpg?x-oss-process=image/resize,w_332","sharePic":"https://imagecloud.thepaper.cn/thepaper/image/331/248/732.jpg","pubTime":"21小时前","pubTimeNew":"21小时前","name":"单价超15万的豪宅，今年已成交超2000套！谁在扫货上海豪宅？","closePraise":"0","nodeInfo":{"nodeId":25433,"name":"地产界","desc":"地产界所有你想知道的事儿","pic":"https://imagecloud.thepaper.cn/thepaper/image/4/158/86.png","nodeType":0,"channelType":0,"forwordType":22,"forwardType":"22","liveType":"1","parentId":25388,"isOrder":"0","dataType":"0","shareName":"地产界","nickName":"","mobForwardType":"22","summarize":"提供地产界最新的投资趋势、最热的地区规划、最深入的政策解读。","color":"","videoLivingRoomDes":"","wwwSpecNodeAlign":0,"govAffairsType":"","showSpecialBanner":false,"showSpecialTopDesc":false,"topBarTypeCustomColor":false,"showVideoBottomRightBtn":false},"nodeId":25433,"contType":0,"pubTimeLong":1732670649794,"specialNodeId":0,"cardMode":"101","dataObjId":52,"closeFrontComment":false,"isSupInteraction":false,"tagList":[{"tagId":20845,"tag":"上海豪宅","isOrder":"0","isUpdateNotify":"0","isWonderfulComments":"0"}],"hideVideoFlag":false,"praiseStyle":1,"isSustainedFly":0,"softLocType":1,"closeComment":false,"voiceInfo":{"imgSrc":"https://imagecloud.thepaper.cn/thepaper/image/331/248/732.jpg","isHaveVoice":"1"},"softAdTypeStr":"1,1,1"},{"contId":"29469631","isOutForword":"0","isOutForward":"0","forwardType":"0","mobForwardType":2,"interactionNum":"81","praiseTimes":"105","pic":"https://imagecloud.thepaper.cn/thepaper/image/331/339/406.jpg","imgCardMode":0,"smallPic":"https://imagecloud.thepaper.cn/thepaper/image/331/339/406.jpg?x-oss-process=image/resize,w_332","sharePic":"https://imagecloud.thepaper.cn/thepaper/image/331/339/407.jpg","pubTime":"23小时前","pubTimeNew":"23小时前","name":"人民日报仲音：全力保障人民群众生命安全和社会稳定","closePraise":"0","nodeInfo":{"nodeId":25489,"name":"舆论场","desc":"倾听复杂世界的弦外之音","pic":"https://imagecloud.thepaper.cn/thepaper/image/4/158/63.png","nodeType":0,"channelType":0,"forwordType":22,"forwardType":"22","liveType":"2","parentId":25388,"isOrder":"0","dataType":"0","shareName":"舆论场","nickName":"","mobForwardType":"22","summarize":"无论是微博、微信，还是报刊阵地，舆论从来不是铁板一块，意见争论绝无对错之分，我们剖析一场舆论风暴如何发酵，力图每个节点都清晰可循。","color":"","videoLivingRoomDes":"","wwwSpecNodeAlign":0,"govAffairsType":"","showSpecialBanner":false,"showSpecialTopDesc":false,"topBarTypeCustomColor":false,"showVideoBottomRightBtn":false},"nodeId":25489,"contType":0,"pubTimeLong":1732661211934,"specialNodeId":0,"cardMode":"101","dataObjId":52,"closeFrontComment":false,"isSupInteraction":false,"tagList":[{"tagId":2247,"tag":"安全稳定","isOrder":"0","isUpdateNotify":"0","isWonderfulComments":"0"}],"hideVideoFlag":false,"praiseStyle":1,"isSustainedFly":0,"softLocType":1,"closeComment":false,"voiceInfo":{"imgSrc":"https://imagecloud.thepaper.cn/thepaper/image/331/339/407.jpg","isHaveVoice":"1"},"softAdTypeStr":"1,1,1"},{"contId":"29467119","isOutForword":"0","isOutForward":"0","forwardType":"0","mobForwardType":2,"interactionNum":"78","praiseTimes":"62","pic":"https://imagecloud.thepaper.cn/thepaper/image/331/308/773.jpg","imgCardMode":0,"smallPic":"https://imagecloud.thepaper.cn/thepaper/image/331/308/773.jpg?x-oss-process=image/resize,w_332","sharePic":"https://imagecloud.thepaper.cn/thepaper/image/331/308/774.jpg","pubTime":"1天前","pubTimeNew":"1天前","name":"以色列安全内阁批准同黎真主党的停火协议","closePraise":"0","waterMark":{"type":"4","value":"1","bigPicValue":"1"},"nodeInfo":{"nodeId":25429,"name":"全球速报","desc":"最热点的全球资讯","pic":"https://imagecloud.thepaper.cn/thepaper/image/4/158/73.png","nodeType":0,"channelType":0,"forwordType":22,"forwardType":"22","liveType":"2","parentId":25388,"isOrder":"0","dataType":"0","shareName":"全球速报","nickName":"","publishTime":1668726066292,"mobForwardType":"22","summarize":"最热点的全球资讯","color":"","videoLivingRoomDes":"","wwwSpecNodeAlign":0,"govAffairsType":"","showSpecialBanner":false,"showSpecialTopDesc":false,"topBarTypeCustomColor":false,"showVideoBottomRightBtn":false},"nodeId":25429,"contType":0,"pubTimeLong":1732649016884,"specialNodeId":0,"cardMode":"101","dataObjId":52,"closeFrontComment":false,"isSupInteraction":false,"tagList":[{"tagId":4646,"tag":"以色列","isOrder":"0","isUpdateNotify":"0","isWonderfulComments":"0"},{"tagId":1098234,"tag":"黎巴嫩真主党","isOrder":"0","isUpdateNotify":"0","isWonderfulComments":"0"},{"tagId":4074,"tag":"伊朗","isOrder":"0","isUpdateNotify":"0","isWonderfulComments":"0"},{"tagId":11878,"tag":"停火协议","isOrder":"0","isUpdateNotify":"0","isWonderfulComments":"0"}],"hideVideoFlag":false,"praiseStyle":1,"isSustainedFly":0,"softLocType":1,"closeComment":false,"voiceInfo":{"imgSrc":"https://imagecloud.thepaper.cn/thepaper/image/331/308/774.jpg","isHaveVoice":"1"},"softAdTypeStr":"1,1,1"},{"contId":"29471500","isOutForword":"0","isOutForward":"0","forwardType":"0","mobForwardType":2,"interactionNum":"166","praiseTimes":"293","pic":"https://imagecloud.thepaper.cn/thepaper/image/331/364/116.jpg","imgCardMode":0,"smallPic":"https://imagecloud.thepaper.cn/thepaper/image/331/364/116.jpg?x-oss-process=image/resize,w_332","sharePic":"https://imagecloud.thepaper.cn/thepaper/image/331/364/117.jpg","pubTime":"15小时前","pubTimeNew":"15小时前","name":"网红“麦琪啦”带货的美国进口产品或为“假洋品牌”：商标注册在国内","closePraise":"0","nodeInfo":{"nodeId":25428,"name":"直击现场","desc":"第一现场，文图视频直播","pic":"https://imagecloud.thepaper.cn/thepaper/image/4/158/70.png","nodeType":0,"channelType":0,"forwordType":22,"forwardType":"22","liveType":"2","parentId":25388,"isOrder":"0","dataType":"0","shareName":"直击现场","nickName":"","mobForwardType":"22","summarize":"最快的现场新闻，最全的现场记录。我是你的眼睛，我就在现场。","color":"","videoLivingRoomDes":"","wwwSpecNodeAlign":0,"govAffairsType":"","showSpecialBanner":false,"showSpecialTopDesc":false,"topBarTypeCustomColor":false,"showVideoBottomRightBtn":false},"nodeId":25428,"contType":0,"pubTimeLong":1732691135806,"specialNodeId":0,"cardMode":"101","dataObjId":52,"closeFrontComment":false,"isSupInteraction":false,"tagList":[{"tagId":6516087,"tag":"麦琪啦","isOrder":"0","isUpdateNotify":"0","isWonderfulComments":"0"},{"tagId":2137111,"tag":"带货主播","isOrder":"0","isUpdateNotify":"0","isWonderfulComments":"0"}],"hideVideoFlag":false,"praiseStyle":1,"isSustainedFly":0,"softLocType":1,"closeComment":false,"voiceInfo":{"imgSrc":"https://imagecloud.thepaper.cn/thepaper/image/331/364/117.jpg","isHaveVoice":"1"},"softAdTypeStr":"1,1,1"},{"contId":"29463899","isOutForword":"0","isOutForward":"0","forwardType":"0","mobForwardType":2,"interactionNum":"72","praiseTimes":"251","pic":"https://imagecloud.thepaper.cn/thepaper/image/331/269/427.jpg","imgCardMode":0,"smallPic":"https://imagecloud.thepaper.cn/thepaper/image/331/269/427.jpg?x-oss-process=image/resize,w_332","sharePic":"https://imagecloud.thepaper.cn/thepaper/image/331/269/428.jpg","pubTime":"22小时前","pubTimeNew":"22小时前","name":"浙江加快推广“以竹代塑”产品：政府单位办公等场景应选尽选","closePraise":"0","nodeInfo":{"nodeId":25491,"name":"长三角政商","desc":"解读区域政情与财富故事","pic":"https://imagecloud.thepaper.cn/thepaper/image/4/158/69.png","nodeType":0,"channelType":0,"forwordType":22,"forwardType":"22","liveType":"2","parentId":25388,"isOrder":"0","dataType":"0","shareName":"长三角政商","nickName":"","mobForwardType":"22","summarize":"深耕中国最大都市群，阐释、发微、钩沉“富贵门”里形形色色的政情动向与财富故事，以及这块冲积平原对中国政经情势放射的冲击波。","color":"","videoLivingRoomDes":"","wwwSpecNodeAlign":0,"govAffairsType":"","showSpecialBanner":false,"showSpecialTopDesc":false,"topBarTypeCustomColor":false,"showVideoBottomRightBtn":false},"nodeId":25491,"contType":0,"pubTimeLong":1732664081694,"specialNodeId":0,"cardMode":"101","dataObjId":52,"closeFrontComment":false,"isSupInteraction":false,"tagList":[{"tagId":5791849,"tag":"以竹代塑","isOrder":"0","isUpdateNotify":"0","isWonderfulComments":"0"},{"tagId":371,"tag":"浙江","isOrder":"0","isUpdateNotify":"0","isWonderfulComments":"0"}],"hideVideoFlag":false,"praiseStyle":1,"isSustainedFly":0,"softLocType":1,"closeComment":false,"voiceInfo":{"imgSrc":"https://imagecloud.thepaper.cn/thepaper/image/331/269/428.jpg","isHaveVoice":"1"},"softAdTypeStr":"1,1,1"},{"contId":"29472123","isOutForword":"0","isOutForward":"0","forwardType":"0","mobForwardType":2,"interactionNum":"103","praiseTimes":"222","pic":"https://imagecloud.thepaper.cn/thepaper/image/331/367/956.jpg","imgCardMode":0,"smallPic":"https://imagecloud.thepaper.cn/thepaper/image/331/367/956.jpg?x-oss-process=image/resize,w_332","sharePic":"https://imagecloud.thepaper.cn/thepaper/image/331/367/957.jpg","pubTime":"15小时前","pubTimeNew":"15小时前","name":"观察︱一审判决后，知识产权专业人士如何看待“郎”标之争","closePraise":"0","nodeInfo":{"nodeId":25426,"name":"法治中国","desc":"司改风向，法治观察","pic":"https://imagecloud.thepaper.cn/thepaper/image/4/158/66.png","nodeType":0,"channelType":0,"forwordType":22,"forwardType":"22","liveType":"2","parentId":25388,"isOrder":"0","dataType":"0","shareName":"法治中国","nickName":"","mobForwardType":"22","summarize":"观测中央司改风向，记录地方司改探索，剖析热点法律议题，推动国家治理法治化。","color":"","videoLivingRoomDes":"","wwwSpecNodeAlign":0,"govAffairsType":"","showSpecialBanner":false,"showSpecialTopDesc":false,"topBarTypeCustomColor":false,"showVideoBottomRightBtn":false},"nodeId":25426,"contType":0,"pubTimeLong":1732689913866,"specialNodeId":0,"cardMode":"101","dataObjId":52,"closeFrontComment":false,"isSupInteraction":false,"tagList":[{"tagId":11161,"tag":"知识产权","isOrder":"0","isUpdateNotify":"0","isWonderfulComments":"0"},{"tagId":378547,"tag":"郎酒","isOrder":"0","isUpdateNotify":"0","isWonderfulComments":"0"},{"tagId":6520836,"tag":"夜郎古","isOrder":"0","isUpdateNotify":"0","isWonderfulComments":"0"},{"tagId":24483,"tag":"商标","isOrder":"0","isUpdateNotify":"0","isWonderfulComments":"0"}],"hideVideoFlag":false,"praiseStyle":1,"isSustainedFly":0,"softLocType":1,"closeComment":false,"voiceInfo":{"imgSrc":"https://imagecloud.thepaper.cn/thepaper/image/331/367/957.jpg","isHaveVoice":"1"},"softAdTypeStr":"1,1,1"},{"contId":"29465196","isOutForword":"0","isOutForward":"0","forwardType":"0","mobForwardType":2,"interactionNum":"50","praiseTimes":"201","pic":"https://imagecloud.thepaper.cn/thepaper/image/331/354/148.jpg","imgCardMode":0,"smallPic":"https://imagecloud.thepaper.cn/thepaper/image/331/354/148.jpg?x-oss-process=image/resize,w_332","sharePic":"https://imagecloud.thepaper.cn/thepaper/image/331/354/149.jpg","pubTime":"18小时前","pubTimeNew":"18小时前","name":"忠诚、非主流的“工具人”或加剧特朗普2.0“回音壁效应”","closePraise":"0","nodeInfo":{"nodeId":25481,"name":"外交学人","desc":"最顶尖国际政治专家，以中国视角洞悉世界","pic":"https://imagecloud.thepaper.cn/thepaper/image/4/158/76.png","nodeType":0,"channelType":0,"forwordType":22,"forwardType":"22","liveType":"2","parentId":25388,"isOrder":"0","dataType":"0","shareName":"外交学人","nickName":"","publishTime":1668726068550,"mobForwardType":"22","summarize":"汇聚最顶尖国际政治专家，提供世界多元格局下的中国视角。","color":"","videoLivingRoomDes":"","wwwSpecNodeAlign":0,"govAffairsType":"","showSpecialBanner":false,"showSpecialTopDesc":false,"topBarTypeCustomColor":false,"showVideoBottomRightBtn":false},"nodeId":25481,"contType":0,"pubTimeLong":1732680355885,"specialNodeId":0,"cardMode":"101","dataObjId":52,"closeFrontComment":false,"isSupInteraction":false,"tagList":[{"tagId":33,"tag":"美国","isOrder":"0","isUpdateNotify":"0","isWonderfulComments":"0"},{"tagId":6499667,"tag":"特朗普2.0","isOrder":"0","isUpdateNotify":"0","isWonderfulComments":"0"}],"hideVideoFlag":false,"praiseStyle":1,"isSustainedFly":0,"softLocType":1,"closeComment":false,"voiceInfo":{"imgSrc":"https://imagecloud.thepaper.cn/thepaper/image/331/354/149.jpg","isHaveVoice":"1"},"softAdTypeStr":"1,1,1"},{"contId":"29473056","isOutForword":"0","isOutForward":"0","forwardType":"0","mobForwardType":2,"interactionNum":"144","praiseTimes":"32","pic":"https://imagecloud.thepaper.cn/thepaper/image/331/378/589.jpg","imgCardMode":0,"smallPic":"https://imagecloud.thepaper.cn/thepaper/image/331/378/589.jpg?x-oss-process=image/resize,w_332","sharePic":"https://imagecloud.thepaper.cn/thepaper/image/331/378/590.jpg","pubTime":"13小时前","pubTimeNew":"13小时前","name":"受贿超3900万，最高法民一庭原庭长郑学林一审获刑十五年","closePraise":"0","nodeInfo":{"nodeId":25424,"name":"一号专案","desc":"司法个案，法治调查","pic":"https://imagecloud.thepaper.cn/thepaper/image/4/158/67.png","nodeType":0,"channelType":0,"forwordType":22,"forwardType":"22","liveType":"2","parentId":25388,"isOrder":"0","dataType":"0","shareName":"一号专案","nickName":"","mobForwardType":"22","summarize":"发掘大、要、新、奇司法个案，以独立专业调查、敏锐细致观察，创建新的政法新闻报道范式。","color":"","videoLivingRoomDes":"","wwwSpecNodeAlign":0,"govAffairsType":"","showSpecialBanner":false,"showSpecialTopDesc":false,"topBarTypeCustomColor":false,"showVideoBottomRightBtn":false},"nodeId":25424,"contType":0,"pubTimeLong":1732698101077,"specialNodeId":0,"cardMode":"101","dataObjId":52,"closeFrontComment":false,"isSupInteraction":false,"tagList":[{"tagId":3374171,"tag":"郑学林","isOrder":"0","isUpdateNotify":"0","isWonderfulComments":"0"}],"hideVideoFlag":false,"praiseStyle":1,"isSustainedFly":0,"softLocType":1,"closeComment":false,"voiceInfo":{"imgSrc":"https://imagecloud.thepaper.cn/thepaper/image/331/378/590.jpg","isHaveVoice":"1"},"softAdTypeStr":"1,1,1"},{"contId":"29473089","isOutForword":"0","isOutForward":"0","forwardType":"0","mobForwardType":2,"interactionNum":"116","praiseTimes":"34","pic":"https://imagecloud.thepaper.cn/thepaper/image/331/379/75.jpg","imgCardMode":0,"smallPic":"https://imagecloud.thepaper.cn/thepaper/image/331/379/75.jpg?x-oss-process=image/resize,w_332","sharePic":"https://imagecloud.thepaper.cn/thepaper/image/331/379/76.jpg","pubTime":"13小时前","pubTimeNew":"13小时前","name":"受贿超8474万，安徽省人大常委会财经委原副主任孔祥喜一审获刑14年","closePraise":"0","nodeInfo":{"nodeId":25424,"name":"一号专案","desc":"司法个案，法治调查","pic":"https://imagecloud.thepaper.cn/thepaper/image/4/158/67.png","nodeType":0,"channelType":0,"forwordType":22,"forwardType":"22","liveType":"2","parentId":25388,"isOrder":"0","dataType":"0","shareName":"一号专案","nickName":"","mobForwardType":"22","summarize":"发掘大、要、新、奇司法个案，以独立专业调查、敏锐细致观察，创建新的政法新闻报道范式。","color":"","videoLivingRoomDes":"","wwwSpecNodeAlign":0,"govAffairsType":"","showSpecialBanner":false,"showSpecialTopDesc":false,"topBarTypeCustomColor":false,"showVideoBottomRightBtn":false},"nodeId":25424,"contType":0,"pubTimeLong":1732698273103,"specialNodeId":0,"cardMode":"101","dataObjId":52,"closeFrontComment":false,"isSupInteraction":false,"tagList":[{"tagId":1963,"tag":"受贿","isOrder":"0","isUpdateNotify":"0","isWonderfulComments":"0"},{"tagId":56874,"tag":"安徽反腐","isOrder":"0","isUpdateNotify":"0","isWonderfulComments":"0"}],"hideVideoFlag":false,"praiseStyle":1,"isSustainedFly":0,"softLocType":1,"closeComment":false,"voiceInfo":{"imgSrc":"https://imagecloud.thepaper.cn/thepaper/image/331/379/76.jpg","isHaveVoice":"1"},"softAdTypeStr":"1,1,1"},{"contId":"29473322","isOutForword":"0","isOutForward":"0","forwardType":"0","mobForwardType":2,"interactionNum":"50","praiseTimes":"73","pic":"https://imagecloud.thepaper.cn/thepaper/image/331/383/900.jpg","imgCardMode":0,"smallPic":"https://imagecloud.thepaper.cn/thepaper/image/331/383/900.jpg?x-oss-process=image/resize,w_332","sharePic":"https://imagecloud.thepaper.cn/thepaper/image/331/383/902.jpg","pubTime":"12小时前","pubTimeNew":"12小时前","name":"医院之间检查检验结果互认的原则是什么，有哪些例外？国家卫健委答澎湃","closePraise":"0","nodeInfo":{"nodeId":25425,"name":"绿政公署","desc":"环境与公共健康调查","pic":"https://imagecloud.thepaper.cn/thepaper/image/4/158/72.png","nodeType":0,"channelType":0,"forwordType":22,"forwardType":"22","liveType":"2","parentId":25388,"isOrder":"0","dataType":"0","shareName":"绿政公署","nickName":"","mobForwardType":"22","summarize":"专注环境领域调查，曝光公共健康隐患。公众都有免于恐惧的自由，万物都有健康生长的权利。","color":"","videoLivingRoomDes":"","wwwSpecNodeAlign":0,"govAffairsType":"","showSpecialBanner":false,"showSpecialTopDesc":false,"topBarTypeCustomColor":false,"showVideoBottomRightBtn":false},"nodeId":25425,"contType":0,"pubTimeLong":1732700067797,"specialNodeId":0,"cardMode":"101","dataObjId":52,"closeFrontComment":false,"isSupInteraction":false,"tagList":[{"tagId":845972,"tag":"国家卫健委","isOrder":"0","isUpdateNotify":"0","isWonderfulComments":"0"},{"tagId":6520619,"tag":"医疗机构检查检验结果互认","isOrder":"0","isUpdateNotify":"0","isWonderfulComments":"0"}],"hideVideoFlag":false,"praiseStyle":1,"isSustainedFly":0,"softLocType":1,"closeComment":false,"voiceInfo":{"imgSrc":"https://imagecloud.thepaper.cn/thepaper/image/331/383/902.jpg","isHaveVoice":"1"},"softAdTypeStr":"1,1,1"},{"contId":"29473672","isOutForword":"0","isOutForward":"0","forwardType":"0","mobForwardType":2,"interactionNum":"40","praiseTimes":"108","pic":"https://imagecloud.thepaper.cn/thepaper/image/331/385/547.JPG","imgCardMode":0,"smallPic":"https://imagecloud.thepaper.cn/thepaper/image/331/385/547.JPG?x-oss-process=image/resize,w_332","sharePic":"https://imagecloud.thepaper.cn/thepaper/image/331/385/548.JPG","pubTime":"10小时前","pubTimeNew":"10小时前","name":"数万元游学团孩子清一色在路边刷手机？文旅部发文规范研学游市场：明确课程、师资","closePraise":"0","nodeInfo":{"nodeId":25433,"name":"地产界","desc":"地产界所有你想知道的事儿","pic":"https://imagecloud.thepaper.cn/thepaper/image/4/158/86.png","nodeType":0,"channelType":0,"forwordType":22,"forwardType":"22","liveType":"1","parentId":25388,"isOrder":"0","dataType":"0","shareName":"地产界","nickName":"","mobForwardType":"22","summarize":"提供地产界最新的投资趋势、最热的地区规划、最深入的政策解读。","color":"","videoLivingRoomDes":"","wwwSpecNodeAlign":0,"govAffairsType":"","showSpecialBanner":false,"showSpecialTopDesc":false,"topBarTypeCustomColor":false,"showVideoBottomRightBtn":false},"nodeId":25433,"contType":0,"pubTimeLong":1732709297439,"specialNodeId":0,"cardMode":"101","dataObjId":52,"closeFrontComment":false,"isSupInteraction":false,"tagList":[{"tagId":643081,"tag":"研学游","isOrder":"0","isUpdateNotify":"0","isWonderfulComments":"0"},{"tagId":1011349,"tag":"文旅部","isOrder":"0","isUpdateNotify":"0","isWonderfulComments":"0"}],"hideVideoFlag":false,"praiseStyle":1,"isSustainedFly":0,"softLocType":1,"closeComment":false,"voiceInfo":{"imgSrc":"https://imagecloud.thepaper.cn/thepaper/image/331/385/548.JPG","isHaveVoice":"1"},"softAdTypeStr":"1,1,1"},{"contId":"29472829","isOutForword":"0","isOutForward":"0","forwardType":"10","mobForwardType":10,"interactionNum":"37","praiseTimes":"103","pic":"https://imagecloud.thepaper.cn/thepaper/image/331/375/505.jpg","imgCardMode":0,"smallPic":"https://imagecloud.thepaper.cn/thepaper/image/331/375/505.jpg?x-oss-process=image/resize,w_332","sharePic":"https://imagecloud.thepaper.cn/thepaper/image/331/375/508.jpg","pubTime":"11小时前","pubTimeNew":"11小时前","name":"保安被指偷学生外卖半学期，南京审计大学金审学院：会处理","closePraise":"0","waterMark":{"type":"1","value":"00:37","bigPicValue":"00:37","videoSize":"3M流量"},"nodeInfo":{"nodeId":26913,"name":"七环视频","desc":"为了更美好的生活","pic":"https://imagecloud.thepaper.cn/thepaper/image/5/405/208.jpg","nodeType":4,"channelType":0,"forwordType":22,"forwardType":"23","liveType":"2","parentId":26886,"isOrder":"0","dataType":"0","shareName":"七环视频","nickName":"","mobForwardType":"23","summarize":"不满足于琐碎的片段，做有态度的新闻视频。","color":"","videoLivingRoomDes":"","wwwSpecNodeAlign":0,"govAffairsType":"","showSpecialBanner":false,"showSpecialTopDesc":false,"topBarTypeCustomColor":false,"showVideoBottomRightBtn":false},"videos":{"videoId":null,"hdurl":"https://cloudvideo.thepaper.cn/video/a009b1c755e24df99bb12fd4d16184e2/hd/202411271724149002ce2cee2-a366-4b1a-9d77-06bcd8d362e6-0ade8ed6-aa57-659f-8cee-7504d096effd.mp4","url":"https://cloudvideo.thepaper.cn/video/a009b1c755e24df99bb12fd4d16184e2/sd/202411271724149002ce2cee2-a366-4b1a-9d77-06bcd8d362e6-0ade8ed6-aa57-659f-8cee-7504d096effd.mp4","duration":"00:37","coverUrl":"https://imagecloud.thepaper.cn/thepaper/image/cover/20241127/75abc6d9fd1e430d8eada8491280845b-20241127172442110-5903690987644025963-d37f67cd-6e85-4c1a-b1f5-fa0a4bbbf32d.jpg","verticalCoverUrl":null,"bytes":"5127392","hdBytes":"5127392","coverUrlFirstFrame":"http://cloudvideo.thepaper.cn/video/a009b1c755e24df99bb12fd4d16184e2/1000.jpg","verticalVideo":false,"durationNum":37,"videoDes":null,"playInfos":null,"outLink":false},"nodeId":26913,"contType":9,"pubTimeLong":1732704431101,"specialNodeId":0,"cardMode":"101","dataObjId":52,"closeFrontComment":false,"isSupInteraction":false,"tagList":[{"tagId":6521409,"tag":"保安被指偷学生外卖半学期","isOrder":"0","isUpdateNotify":"0","isWonderfulComments":"0"}],"hideVideoFlag":false,"praiseStyle":1,"isSustainedFly":0,"softLocType":1,"closeComment":false,"voiceInfo":{"imgSrc":"https://imagecloud.thepaper.cn/thepaper/image/331/375/508.jpg","isHaveVoice":"0"},"softAdTypeStr":"1,1,1"},{"contId":"29472303","isOutForword":"0","isOutForward":"0","forwardType":"10","mobForwardType":10,"interactionNum":"75","praiseTimes":"13","pic":"https://imagecloud.thepaper.cn/thepaper/image/331/369/842.jpg","imgCardMode":0,"smallPic":"https://imagecloud.thepaper.cn/thepaper/image/331/369/842.jpg?x-oss-process=image/resize,w_332","sharePic":"https://imagecloud.thepaper.cn/thepaper/image/331/369/843.jpg","pubTime":"13小时前","pubTimeNew":"13小时前","name":"“骗保推妻坠海”案细节：丈夫毕业于名校，案发后住酒店招嫖","closePraise":"0","waterMark":{"type":"1","value":"00:40","bigPicValue":"00:40","videoSize":"2M流量"},"nodeInfo":{"nodeId":26913,"name":"七环视频","desc":"为了更美好的生活","pic":"https://imagecloud.thepaper.cn/thepaper/image/5/405/208.jpg","nodeType":4,"channelType":0,"forwordType":22,"forwardType":"23","liveType":"2","parentId":26886,"isOrder":"0","dataType":"0","shareName":"七环视频","nickName":"","mobForwardType":"23","summarize":"不满足于琐碎的片段，做有态度的新闻视频。","color":"","videoLivingRoomDes":"","wwwSpecNodeAlign":0,"govAffairsType":"","showSpecialBanner":false,"showSpecialTopDesc":false,"topBarTypeCustomColor":false,"showVideoBottomRightBtn":false},"videos":{"videoId":null,"hdurl":"https://cloudvideo.thepaper.cn/video/2b8b1dfb997944bd9d4458d9cbc58c7a/hd/20241127161529396c9aa7cdc-23b7-48ed-b154-dfe697b2d15b-b94c0ce5-8b8c-f5f0-f886-6222ee0a9f71.mp4","url":"https://cloudvideo.thepaper.cn/video/2b8b1dfb997944bd9d4458d9cbc58c7a/sd/20241127161529396c9aa7cdc-23b7-48ed-b154-dfe697b2d15b-b94c0ce5-8b8c-f5f0-f886-6222ee0a9f71.mp4","duration":"00:40","coverUrl":"https://imagecloud.thepaper.cn/thepaper/image/cover/20241127/fbea0a13ac274880b3edae0ff027f1e9-20241127161556797-1456914484879228225-aec6730c-f031-4eb7-84a4-61d0f1af7772.jpg","verticalCoverUrl":null,"bytes":"3645024","hdBytes":"6235111","coverUrlFirstFrame":"http://cloudvideo.thepaper.cn/video/2b8b1dfb997944bd9d4458d9cbc58c7a/1000.jpg","verticalVideo":false,"durationNum":40,"videoDes":null,"playInfos":null,"outLink":false},"nodeId":26913,"contType":9,"pubTimeLong":1732696463938,"specialNodeId":0,"cardMode":"101","dataObjId":52,"closeFrontComment":false,"isSupInteraction":false,"tagList":[{"tagId":260813,"tag":"坠海","isOrder":"0","isUpdateNotify":"0","isWonderfulComments":"0"},{"tagId":59972,"tag":"骗保","isOrder":"0","isUpdateNotify":"0","isWonderfulComments":"0"}],"hideVideoFlag":false,"praiseStyle":3,"isSustainedFly":0,"softLocType":1,"closeComment":false,"voiceInfo":{"imgSrc":"https://imagecloud.thepaper.cn/thepaper/image/331/369/843.jpg","isHaveVoice":"0"},"softAdTypeStr":"1,1,1"},{"contId":"29464703","isOutForword":"0","isOutForward":"0","forwardType":"74","mobForwardType":74,"interactionNum":"","praiseTimes":"76","pic":"https://imagecloud.thepaper.cn/thepaper/image/331/280/669.jpg","imgCardMode":0,"smallPic":"https://imagecloud.thepaper.cn/thepaper/image/331/280/669.jpg?x-oss-process=image/resize,w_332","sharePic":"https://imagecloud.thepaper.cn/thepaper/image/331/280/670.jpg","pubTime":"18小时前","pubTimeNew":"18小时前","name":"三亚一老人凌晨摘椰子体力不支，目击者：倒挂2小时有余","closePraise":"0","waterMark":{"type":"1","value":"00:11","bigPicValue":"00:11","videoSize":"1M流量"},"nodeInfo":{"nodeId":26913,"name":"七环视频","desc":"为了更美好的生活","pic":"https://imagecloud.thepaper.cn/thepaper/image/5/405/208.jpg","nodeType":4,"channelType":0,"forwordType":22,"forwardType":"23","liveType":"2","parentId":26886,"isOrder":"0","dataType":"0","shareName":"七环视频","nickName":"","mobForwardType":"23","summarize":"不满足于琐碎的片段，做有态度的新闻视频。","color":"","videoLivingRoomDes":"","wwwSpecNodeAlign":0,"govAffairsType":"","showSpecialBanner":false,"showSpecialTopDesc":false,"topBarTypeCustomColor":false,"showVideoBottomRightBtn":false},"videos":{"videoId":null,"hdurl":"https://cloudvideo.thepaper.cn/video/5f8ec8f31ce34f2a9a178750008442d7/hd/2024112621374901676c57175-830a-4c9c-9449-9fd26c9c399f-949b09dc-88ed-5d3b-b5bc-74c400551daf.mp4","url":"https://cloudvideo.thepaper.cn/video/5f8ec8f31ce34f2a9a178750008442d7/sd/2024112621374901676c57175-830a-4c9c-9449-9fd26c9c399f-949b09dc-88ed-5d3b-b5bc-74c400551daf.mp4","duration":"00:11","coverUrl":"https://imagecloud.thepaper.cn/thepaper/image/cover/20241126/1b762a03f3864b41b6d6c54da0b5365a-20241126213857601-707280532339716507-d7a74717-78ff-4bcb-ae72-2670159b05bd.jpg","verticalCoverUrl":"https://imagecloud.thepaper.cn/thepaper/image/331/280/673.jpg","bytes":"2104057","hdBytes":"3873937","coverUrlFirstFrame":"http://cloudvideo.thepaper.cn/video/5f8ec8f31ce34f2a9a178750008442d7/1000.jpg","verticalVideo":true,"durationNum":11,"videoDes":null,"playInfos":null,"outLink":false},"nodeId":26913,"contType":9,"pubTimeLong":1732679415740,"specialNodeId":0,"cardMode":"101","dataObjId":52,"closeFrontComment":false,"isSupInteraction":false,"tagList":[{"tagId":3331056,"tag":"摘椰子","isOrder":"0","isUpdateNotify":"0","isWonderfulComments":"0"},{"tagId":902682,"tag":"体力不支","isOrder":"0","isUpdateNotify":"0","isWonderfulComments":"0"},{"tagId":6520353,"tag":"倒挂2小时有余","isOrder":"0","isUpdateNotify":"0","isWonderfulComments":"0"}],"hideVideoFlag":false,"praiseStyle":1,"isSustainedFly":0,"softLocType":1,"closeComment":false,"voiceInfo":{"imgSrc":"https://imagecloud.thepaper.cn/thepaper/image/331/280/670.jpg","isHaveVoice":"0"},"softAdTypeStr":"1,1,1"}],"editorHandpicked":[{"contId":"29476781","isOutForword":"0","isOutForward":"0","forwardType":"0","mobForwardType":2,"interactionNum":"31","praiseTimes":"58","pic":"https://imagecloud.thepaper.cn/thepaper/image/331/421/773.jpg","imgCardMode":0,"smallPic":"https://imagecloud.thepaper.cn/thepaper/image/331/421/773.jpg?x-oss-process=image/resize,w_332","sharePic":"https://imagecloud.thepaper.cn/thepaper/image/331/421/774.jpg","pubTime":"7小时前","pubTimeNew":"7小时前","name":"焦点访谈：揭秘几万吨工业盐酸偷排的“隐秘角落”","closePraise":"0","waterMark":{"type":"4","value":"1","bigPicValue":"1"},"nodeInfo":{"nodeId":25425,"name":"绿政公署","desc":"环境与公共健康调查","pic":"https://imagecloud.thepaper.cn/thepaper/image/4/158/72.png","nodeType":0,"channelType":0,"forwordType":22,"forwardType":"22","liveType":"2","parentId":25388,"isOrder":"0","dataType":"0","shareName":"绿政公署","nickName":"","mobForwardType":"22","summarize":"专注环境领域调查，曝光公共健康隐患。公众都有免于恐惧的自由，万物都有健康生长的权利。","color":"","videoLivingRoomDes":"","wwwSpecNodeAlign":0,"govAffairsType":"","showSpecialBanner":false,"showSpecialTopDesc":false,"topBarTypeCustomColor":false,"showVideoBottomRightBtn":false},"nodeId":25425,"contType":0,"pubTimeLong":1732719401817,"specialNodeId":0,"cardMode":"101","dataObjId":52,"closeFrontComment":false,"isSupInteraction":false,"tagList":[{"tagId":273,"tag":"偷排","isOrder":"0","isUpdateNotify":"0","isWonderfulComments":"0"}],"hideVideoFlag":false,"praiseStyle":1,"isSustainedFly":0,"softLocType":1,"closeComment":false,"voiceInfo":{"imgSrc":"https://imagecloud.thepaper.cn/thepaper/image/331/421/774.jpg","isHaveVoice":"1"},"softAdTypeStr":"1,1,1"},{"contId":"29476443","isOutForword":"0","isOutForward":"0","forwardType":"0","mobForwardType":2,"interactionNum":"34","praiseTimes":"3","pic":"https://imagecloud.thepaper.cn/thepaper/image/331/420/153.jpg","imgCardMode":0,"smallPic":"https://imagecloud.thepaper.cn/thepaper/image/331/420/153.jpg?x-oss-process=image/resize,w_332","sharePic":"https://imagecloud.thepaper.cn/thepaper/image/331/420/154.jpg","pubTime":"8小时前","pubTimeNew":"8小时前","name":"广西大新大批野生猕猴进村？当地林业部门：建议用家狗驱赶","closePraise":"0","waterMark":{"type":"4","value":"1","bigPicValue":"1"},"nodeInfo":{"nodeId":25428,"name":"直击现场","desc":"第一现场，文图视频直播","pic":"https://imagecloud.thepaper.cn/thepaper/image/4/158/70.png","nodeType":0,"channelType":0,"forwordType":22,"forwardType":"22","liveType":"2","parentId":25388,"isOrder":"0","dataType":"0","shareName":"直击现场","nickName":"","mobForwardType":"22","summarize":"最快的现场新闻，最全的现场记录。我是你的眼睛，我就在现场。","color":"","videoLivingRoomDes":"","wwwSpecNodeAlign":0,"govAffairsType":"","showSpecialBanner":false,"showSpecialTopDesc":false,"topBarTypeCustomColor":false,"showVideoBottomRightBtn":false},"nodeId":25428,"contType":0,"pubTimeLong":1732716239564,"specialNodeId":0,"cardMode":"101","dataObjId":52,"closeFrontComment":false,"isSupInteraction":false,"tagList":[{"tagId":6521740,"tag":"野生猕猴进村","isOrder":"0","isUpdateNotify":"0","isWonderfulComments":"0"}],"hideVideoFlag":false,"praiseStyle":1,"isSustainedFly":0,"softLocType":1,"closeComment":false,"voiceInfo":{"imgSrc":"https://imagecloud.thepaper.cn/thepaper/image/331/420/154.jpg","isHaveVoice":"1"},"softAdTypeStr":"1,1,1"},{"contId":"29473672","isOutForword":"0","isOutForward":"0","forwardType":"0","mobForwardType":2,"interactionNum":"40","praiseTimes":"108","pic":"https://imagecloud.thepaper.cn/thepaper/image/331/385/547.JPG","imgCardMode":0,"smallPic":"https://imagecloud.thepaper.cn/thepaper/image/331/385/547.JPG?x-oss-process=image/resize,w_332","sharePic":"https://imagecloud.thepaper.cn/thepaper/image/331/385/548.JPG","pubTime":"10小时前","pubTimeNew":"10小时前","name":"数万元游学团孩子清一色在路边刷手机？文旅部发文规范研学游市场：明确课程、师资","closePraise":"0","nodeInfo":{"nodeId":25433,"name":"地产界","desc":"地产界所有你想知道的事儿","pic":"https://imagecloud.thepaper.cn/thepaper/image/4/158/86.png","nodeType":0,"channelType":0,"forwordType":22,"forwardType":"22","liveType":"1","parentId":25388,"isOrder":"0","dataType":"0","shareName":"地产界","nickName":"","mobForwardType":"22","summarize":"提供地产界最新的投资趋势、最热的地区规划、最深入的政策解读。","color":"","videoLivingRoomDes":"","wwwSpecNodeAlign":0,"govAffairsType":"","showSpecialBanner":false,"showSpecialTopDesc":false,"topBarTypeCustomColor":false,"showVideoBottomRightBtn":false},"nodeId":25433,"contType":0,"pubTimeLong":1732709297439,"specialNodeId":0,"cardMode":"101","dataObjId":52,"closeFrontComment":false,"isSupInteraction":false,"tagList":[{"tagId":643081,"tag":"研学游","isOrder":"0","isUpdateNotify":"0","isWonderfulComments":"0"},{"tagId":1011349,"tag":"文旅部","isOrder":"0","isUpdateNotify":"0","isWonderfulComments":"0"}],"hideVideoFlag":false,"praiseStyle":1,"isSustainedFly":0,"softLocType":1,"closeComment":false,"voiceInfo":{"imgSrc":"https://imagecloud.thepaper.cn/thepaper/image/331/385/548.JPG","isHaveVoice":"1"},"softAdTypeStr":"1,1,1"},{"contId":"29473986","isOutForword":"0","isOutForward":"0","forwardType":"0","mobForwardType":2,"interactionNum":"34","praiseTimes":"110","pic":"https://imagecloud.thepaper.cn/thepaper/image/331/387/606.png","imgCardMode":0,"smallPic":"https://imagecloud.thepaper.cn/thepaper/image/331/387/606.png?x-oss-process=image/resize,w_332","sharePic":"https://imagecloud.thepaper.cn/thepaper/image/331/387/607.png","pubTime":"8小时前","pubTimeNew":"8小时前","name":"两家央企合计获批5000亿“稳增长扩投资专项债”，释放了什么信号","closePraise":"0","nodeInfo":{"nodeId":25435,"name":"金改实验室","desc":"金融创新灵感集散地","pic":"https://imagecloud.thepaper.cn/thepaper/image/4/158/88.png","nodeType":0,"channelType":0,"forwordType":22,"forwardType":"22","liveType":"2","parentId":25388,"isOrder":"0","dataType":"0","shareName":"金改实验室","nickName":"","mobForwardType":"22","summarize":"我们专注于为你聚合地方金融改革、新兴金融业态等金融创新相关的信息，希望能成为对你有用的“金融创新灵感集散地”。","color":"","videoLivingRoomDes":"","wwwSpecNodeAlign":0,"govAffairsType":"","showSpecialBanner":false,"showSpecialTopDesc":false,"topBarTypeCustomColor":false,"showVideoBottomRightBtn":false},"nodeId":25435,"contType":0,"pubTimeLong":1732714193907,"specialNodeId":0,"cardMode":"101","dataObjId":52,"closeFrontComment":false,"isSupInteraction":false,"tagList":[{"tagId":6521698,"tag":"稳增长扩投资专项债","isOrder":"0","isUpdateNotify":"0","isWonderfulComments":"0"},{"tagId":112,"tag":"央企","isOrder":"0","isUpdateNotify":"0","isWonderfulComments":"0"},{"tagId":317415,"tag":"国有资本运营公司","isOrder":"0","isUpdateNotify":"0","isWonderfulComments":"0"}],"hideVideoFlag":false,"praiseStyle":1,"isSustainedFly":0,"softLocType":1,"closeComment":false,"voiceInfo":{"imgSrc":"https://imagecloud.thepaper.cn/thepaper/image/331/387/607.png","isHaveVoice":"1"},"softAdTypeStr":"1,1,1"},{"contId":"29475744","isOutForword":"0","isOutForward":"0","forwardType":"0","mobForwardType":2,"interactionNum":"94","praiseTimes":"61","pic":"https://imagecloud.thepaper.cn/thepaper/image/331/412/771.jpg","imgCardMode":0,"smallPic":"https://imagecloud.thepaper.cn/thepaper/image/331/412/771.jpg?x-oss-process=image/resize,w_332","sharePic":"https://imagecloud.thepaper.cn/thepaper/image/331/412/773.jpg","pubTime":"8小时前","pubTimeNew":"8小时前","name":"内蒙古警察枪击案重审庭审结束，法院将择期宣判","closePraise":"0","nodeInfo":{"nodeId":25424,"name":"一号专案","desc":"司法个案，法治调查","pic":"https://imagecloud.thepaper.cn/thepaper/image/4/158/67.png","nodeType":0,"channelType":0,"forwordType":22,"forwardType":"22","liveType":"2","parentId":25388,"isOrder":"0","dataType":"0","shareName":"一号专案","nickName":"","mobForwardType":"22","summarize":"发掘大、要、新、奇司法个案，以独立专业调查、敏锐细致观察，创建新的政法新闻报道范式。","color":"","videoLivingRoomDes":"","wwwSpecNodeAlign":0,"govAffairsType":"","showSpecialBanner":false,"showSpecialTopDesc":false,"topBarTypeCustomColor":false,"showVideoBottomRightBtn":false},"nodeId":25424,"contType":0,"pubTimeLong":1732714502465,"specialNodeId":0,"cardMode":"101","dataObjId":52,"closeFrontComment":false,"isSupInteraction":false,"tagList":[{"tagId":8676,"tag":"枪击案","isOrder":"0","isUpdateNotify":"0","isWonderfulComments":"0"}],"hideVideoFlag":false,"praiseStyle":1,"isSustainedFly":0,"softLocType":1,"closeComment":false,"voiceInfo":{"imgSrc":"https://imagecloud.thepaper.cn/thepaper/image/331/412/773.jpg","isHaveVoice":"1"},"softAdTypeStr":"1,1,1"},{"contId":"29473322","isOutForword":"0","isOutForward":"0","forwardType":"0","mobForwardType":2,"interactionNum":"50","praiseTimes":"73","pic":"https://imagecloud.thepaper.cn/thepaper/image/331/383/900.jpg","imgCardMode":0,"smallPic":"https://imagecloud.thepaper.cn/thepaper/image/331/383/900.jpg?x-oss-process=image/resize,w_332","sharePic":"https://imagecloud.thepaper.cn/thepaper/image/331/383/902.jpg","pubTime":"12小时前","pubTimeNew":"12小时前","name":"医院之间检查检验结果互认的原则是什么，有哪些例外？国家卫健委答澎湃","closePraise":"0","nodeInfo":{"nodeId":25425,"name":"绿政公署","desc":"环境与公共健康调查","pic":"https://imagecloud.thepaper.cn/thepaper/image/4/158/72.png","nodeType":0,"channelType":0,"forwordType":22,"forwardType":"22","liveType":"2","parentId":25388,"isOrder":"0","dataType":"0","shareName":"绿政公署","nickName":"","mobForwardType":"22","summarize":"专注环境领域调查，曝光公共健康隐患。公众都有免于恐惧的自由，万物都有健康生长的权利。","color":"","videoLivingRoomDes":"","wwwSpecNodeAlign":0,"govAffairsType":"","showSpecialBanner":false,"showSpecialTopDesc":false,"topBarTypeCustomColor":false,"showVideoBottomRightBtn":false},"nodeId":25425,"contType":0,"pubTimeLong":1732700067797,"specialNodeId":0,"cardMode":"101","dataObjId":52,"closeFrontComment":false,"isSupInteraction":false,"tagList":[{"tagId":845972,"tag":"国家卫健委","isOrder":"0","isUpdateNotify":"0","isWonderfulComments":"0"},{"tagId":6520619,"tag":"医疗机构检查检验结果互认","isOrder":"0","isUpdateNotify":"0","isWonderfulComments":"0"}],"hideVideoFlag":false,"praiseStyle":1,"isSustainedFly":0,"softLocType":1,"closeComment":false,"voiceInfo":{"imgSrc":"https://imagecloud.thepaper.cn/thepaper/image/331/383/902.jpg","isHaveVoice":"1"},"softAdTypeStr":"1,1,1"},{"contId":"29476294","isOutForword":"0","isOutForward":"0","forwardType":"74","mobForwardType":74,"interactionNum":"","praiseTimes":"123","pic":"https://imagecloud.thepaper.cn/thepaper/image/331/415/571.jpg","imgCardMode":0,"smallPic":"https://imagecloud.thepaper.cn/thepaper/image/331/415/571.jpg?x-oss-process=image/resize,w_332","sharePic":"https://imagecloud.thepaper.cn/thepaper/image/331/415/572.jpg","pubTime":"8小时前","pubTimeNew":"8小时前","name":"连线｜在黎华人：“骗”孩子爆炸声是放礼花，盼永久停火苦难不复","closePraise":"0","waterMark":{"type":"1","value":"01:58","bigPicValue":"01:58","videoSize":"8M流量"},"nodeInfo":{"nodeId":122906,"name":"World全知道","desc":"打败时差，在这里看到世界","pic":"https://imagecloud.thepaper.cn/thepaper/image/225/728/333.png","nodeType":0,"channelType":0,"forwordType":22,"forwardType":"22","liveType":"","parentId":26886,"isOrder":"0","dataType":"0","shareName":"World全知道","nickName":"","publishTime":1668726199449,"mobForwardType":"22","summarize":"打败时差，在这里看到世界","color":"","videoLivingRoomDes":"","wwwSpecNodeAlign":0,"govAffairsType":"","showSpecialBanner":false,"showSpecialTopDesc":false,"topBarTypeCustomColor":false,"showVideoBottomRightBtn":false},"videos":{"videoId":null,"hdurl":"https://cloudvideo.thepaper.cn/video/b43528df46d743cda865838e183852b6/hd/2024112721332865852512e42-7adf-4461-aaed-f6a03e83774b-0fa4e326-3d29-668c-c8c0-6cf0ed13e89d.mp4","url":"https://cloudvideo.thepaper.cn/video/b43528df46d743cda865838e183852b6/sd/2024112721332865852512e42-7adf-4461-aaed-f6a03e83774b-0fa4e326-3d29-668c-c8c0-6cf0ed13e89d.mp4","duration":"01:58","coverUrl":"https://imagecloud.thepaper.cn/thepaper/image/cover/20241127/13180e7edbfe43749119f3d5619eb7c7-20241127213419382-6399008177903939818-eb449e34-9a48-43d7-8380-da15b63529be.jpg","verticalCoverUrl":null,"bytes":"15062134","hdBytes":"27471581","coverUrlFirstFrame":"http://cloudvideo.thepaper.cn/video/b43528df46d743cda865838e183852b6/1000.jpg","verticalVideo":true,"durationNum":118,"videoDes":null,"playInfos":null,"outLink":false},"nodeId":122906,"contType":9,"pubTimeLong":1732715643988,"specialNodeId":0,"cardMode":"101","dataObjId":52,"closeFrontComment":false,"isSupInteraction":false,"tagList":[{"tagId":2790281,"tag":"黎以冲突","isOrder":"0","isUpdateNotify":"0","isWonderfulComments":"0"},{"tagId":6521376,"tag":"黎以停火","isOrder":"0","isUpdateNotify":"0","isWonderfulComments":"0"},{"tagId":654564,"tag":"贝鲁特","isOrder":"0","isUpdateNotify":"0","isWonderfulComments":"0"},{"tagId":6410788,"tag":"在黎华人","isOrder":"0","isUpdateNotify":"0","isWonderfulComments":"0"}],"hideVideoFlag":false,"praiseStyle":1,"isSustainedFly":0,"softLocType":1,"closeComment":false,"voiceInfo":{"imgSrc":"https://imagecloud.thepaper.cn/thepaper/image/331/415/572.jpg","isHaveVoice":"0"},"softAdTypeStr":"1,1,1"},{"contId":"29469732","isOutForword":"0","isOutForward":"0","forwardType":"0","mobForwardType":2,"interactionNum":"25","praiseTimes":"68","pic":"https://imagecloud.thepaper.cn/thepaper/image/331/341/8.jpg","imgCardMode":0,"smallPic":"https://imagecloud.thepaper.cn/thepaper/image/331/341/8.jpg?x-oss-process=image/resize,w_332","sharePic":"https://imagecloud.thepaper.cn/thepaper/image/331/341/10.jpg","pubTime":"12小时前","pubTimeNew":"12小时前","name":"一只“熊孩子”，成为沪上“西郊顶流”","closePraise":"0","waterMark":{"type":"4","value":"1","bigPicValue":"1"},"nodeInfo":{"nodeId":25422,"name":"浦江头条","desc":"上海每天最重要的事件","pic":"https://imagecloud.thepaper.cn/thepaper/image/4/158/81.png","nodeType":0,"channelType":0,"forwordType":22,"forwardType":"22","liveType":"1","parentId":25388,"isOrder":"0","dataType":"0","shareName":"浦江头条","nickName":"","mobForwardType":"22","recommendIds":[13851102],"summarize":"不满足于最动态，还要最重要；丰富而不琐碎，快速但不轻浮。你最想关注的上海新闻，这里肯定有，你应该知道的上海新闻，这里也会有。","color":"","videoLivingRoomDes":"","wwwSpecNodeAlign":0,"govAffairsType":"","showSpecialBanner":false,"showSpecialTopDesc":false,"topBarTypeCustomColor":false,"showVideoBottomRightBtn":false},"nodeId":25422,"contType":0,"pubTimeLong":1732702904597,"specialNodeId":0,"cardMode":"101","dataObjId":52,"closeFrontComment":false,"isSupInteraction":false,"tagList":[{"tagId":34995,"tag":"上海动物园","isOrder":"0","isUpdateNotify":"0","isWonderfulComments":"0"},{"tagId":321856,"tag":"棕熊","isOrder":"0","isUpdateNotify":"0","isWonderfulComments":"0"},{"tagId":230446,"tag":"达菲","isOrder":"0","isUpdateNotify":"0","isWonderfulComments":"0"}],"hideVideoFlag":false,"praiseStyle":1,"isSustainedFly":0,"softLocType":1,"closeComment":false,"voiceInfo":{"imgSrc":"https://imagecloud.thepaper.cn/thepaper/image/331/341/10.jpg","isHaveVoice":"1"},"softAdTypeStr":"1,1,1"},{"contId":"29473326","isOutForword":"0","isOutForward":"0","forwardType":"0","mobForwardType":2,"interactionNum":"97","praiseTimes":"16","pic":"https://imagecloud.thepaper.cn/thepaper/image/331/382/535.jpg","imgCardMode":0,"smallPic":"https://imagecloud.thepaper.cn/thepaper/image/331/382/535.jpg?x-oss-process=image/resize,w_332","sharePic":"https://imagecloud.thepaper.cn/thepaper/image/331/382/536.jpg","pubTime":"12小时前","pubTimeNew":"12小时前","name":"【社论】让群众看病少跑路、少检查、少花钱","closePraise":"0","nodeInfo":{"nodeId":25444,"name":"社论","desc":"澎湃的立场","pic":"https://imagecloud.thepaper.cn/thepaper/image/4/158/103.png","nodeType":0,"channelType":0,"forwordType":22,"forwardType":"22","liveType":"2","parentId":25389,"isOrder":"0","dataType":"0","shareName":"社论","nickName":"","mobForwardType":"22","summarize":"19:30，告诉你我们最想说的话。","color":"","videoLivingRoomDes":"","wwwSpecNodeAlign":0,"govAffairsType":"","showSpecialBanner":false,"showSpecialTopDesc":false,"topBarTypeCustomColor":false,"showVideoBottomRightBtn":false},"nodeId":25444,"contType":0,"pubTimeLong":1732700492750,"specialNodeId":0,"cardMode":"101","dataObjId":52,"closeFrontComment":false,"isSupInteraction":false,"tagList":[{"tagId":5850725,"tag":"医检互认","isOrder":"0","isUpdateNotify":"0","isWonderfulComments":"0"},{"tagId":5031220,"tag":"看病就医","isOrder":"0","isUpdateNotify":"0","isWonderfulComments":"0"}],"hideVideoFlag":false,"praiseStyle":1,"isSustainedFly":0,"softLocType":1,"closeComment":false,"voiceInfo":{"imgSrc":"https://imagecloud.thepaper.cn/thepaper/image/331/382/536.jpg","isHaveVoice":"1"},"softAdTypeStr":"1,1,1"},{"contId":"29473089","isOutForword":"0","isOutForward":"0","forwardType":"0","mobForwardType":2,"interactionNum":"116","praiseTimes":"34","pic":"https://imagecloud.thepaper.cn/thepaper/image/331/379/75.jpg","imgCardMode":0,"smallPic":"https://imagecloud.thepaper.cn/thepaper/image/331/379/75.jpg?x-oss-process=image/resize,w_332","sharePic":"https://imagecloud.thepaper.cn/thepaper/image/331/379/76.jpg","pubTime":"13小时前","pubTimeNew":"13小时前","name":"受贿超8474万，安徽省人大常委会财经委原副主任孔祥喜一审获刑14年","closePraise":"0","nodeInfo":{"nodeId":25424,"name":"一号专案","desc":"司法个案，法治调查","pic":"https://imagecloud.thepaper.cn/thepaper/image/4/158/67.png","nodeType":0,"channelType":0,"forwordType":22,"forwardType":"22","liveType":"2","parentId":25388,"isOrder":"0","dataType":"0","shareName":"一号专案","nickName":"","mobForwardType":"22","summarize":"发掘大、要、新、奇司法个案，以独立专业调查、敏锐细致观察，创建新的政法新闻报道范式。","color":"","videoLivingRoomDes":"","wwwSpecNodeAlign":0,"govAffairsType":"","showSpecialBanner":false,"showSpecialTopDesc":false,"topBarTypeCustomColor":false,"showVideoBottomRightBtn":false},"nodeId":25424,"contType":0,"pubTimeLong":1732698273103,"specialNodeId":0,"cardMode":"101","dataObjId":52,"closeFrontComment":false,"isSupInteraction":false,"tagList":[{"tagId":1963,"tag":"受贿","isOrder":"0","isUpdateNotify":"0","isWonderfulComments":"0"},{"tagId":56874,"tag":"安徽反腐","isOrder":"0","isUpdateNotify":"0","isWonderfulComments":"0"}],"hideVideoFlag":false,"praiseStyle":1,"isSustainedFly":0,"softLocType":1,"closeComment":false,"voiceInfo":{"imgSrc":"https://imagecloud.thepaper.cn/thepaper/image/331/379/76.jpg","isHaveVoice":"1"},"softAdTypeStr":"1,1,1"}]}}